{"AA":{"MEANINGS":{"1":["Noun","a dry form of lava resembling clinkers"]},"SYNONYMS":["Aa","Alcoholics anonymous","Associate in arts"]},"AAH":{"MEANINGS":{},"SYNONYMS":["Aah","Ooh"]},"AAHED":{"MEANINGS":{},"SYNONYMS":["Aah","Ooh"]},"AAHING":{"MEANINGS":{},"SYNONYMS":["Aah","Ooh"]},"AAHS":{"MEANINGS":{},"SYNONYMS":["Aah","Ooh"]},"AALII":{"MEANINGS":{"1":["Noun","a small Hawaiian tree with hard dark wood",["Tree"],[]]},"SYNONYMS":["Aalii"]},"AALIIS":{"MEANINGS":{},"SYNONYMS":["Aalii"]},"AARDVARK":{"MEANINGS":{"1":["Noun","nocturnal burrowing mammal of the grasslands of Africa that feeds on termites; sole extant representative of the order Tubulidentata",["Placental","Placental mammal","Eutherian","Eutherian mammal"],[]]},"SYNONYMS":["Orycteropus afer","Ant bear","Anteater","Aardvark"]},"AARDVARKS":{"MEANINGS":{},"SYNONYMS":["Orycteropus afer","Ant bear","Anteater","Aardvark"]},"AARDWOLF":{"MEANINGS":{"1":["Noun","striped hyena of southeast Africa that feeds chiefly on insects",["Hyena","Hyaena"],[]]},"SYNONYMS":["Proteles cristata","Aardwolf"]},"AARDWOLVES":{"MEANINGS":{},"SYNONYMS":["Proteles cristata","Aardwolf"]},"AB":{"MEANINGS":{"2":["Noun","the eleventh month of the civil year; the fifth month of the ecclesiastical year in the Jewish calendar (in July and August)",["Jewish calendar month"],[]],"4":["Noun","the blood group whose red cells carry both the A and B antigens",["Blood group","Blood type"],[]]},"SYNONYMS":["Group ab","Abdominal","Type ab","Ab","Abdominal muscle"]},"ABA":{"MEANINGS":{"1":["Noun","a loose sleeveless outer garment made from aba cloth; worn by Arabs",["Overgarment","Outer garment"],[]],"2":["Noun","a fabric woven from goat hair and camel hair",["Fabric","Cloth","Material","Textile"],[]]},"SYNONYMS":["Aba"]},"ABACA":{"MEANINGS":{"2":["Noun","Philippine banana tree having leafstalks that yield Manila hemp used for rope and paper etc",["Banana","Banana tree"],[]]},"SYNONYMS":["Manila hemp","Abaca","Musa textilis","Manilla hemp"]},"ABACAS":{"MEANINGS":{},"SYNONYMS":["Manila hemp","Abaca","Musa textilis","Manilla hemp"]},"ABACI":{"MEANINGS":{},"SYNONYMS":["Abacus"]},"ABACINATE":{"MEANINGS":{"1":["Verb","blind by holding a red-hot metal plate before someone's eyes",["Blind"],["The prisoners were abacinated by their captors"]]},"SYNONYMS":["Abacinate"]},"ABACK":{"MEANINGS":{"1":["Adverb","having the wind against the forward side of the sails",[],["the ship came up into the wind with all yards aback"]],"2":["Adverb","by surprise",[],["taken aback by the caustic remarks"]]},"SYNONYMS":["Aback"]},"ABACTINAL":{"MEANINGS":{"1":["Adjective","(of radiate animals) located on the surface or end opposite to that on which the mouth is situated",[],[]]},"ANTONYMS":["actinal"],"SYNONYMS":["Abactinal"]},"ABACUS":{"MEANINGS":{"1":["Noun","a tablet placed horizontally on top of the capital of a column as an aid in supporting the architrave",["Tablet"],[]],"2":["Noun","a calculator that performs arithmetic functions by manually sliding counters on rods or in grooves",["Calculator","Calculating machine"],[]]},"SYNONYMS":["Abacus"]},"ABACUSES":{"MEANINGS":{},"SYNONYMS":["Abacus"]},"ABAFT":{"MEANINGS":{},"ANTONYMS":["fore"],"SYNONYMS":["Abaft","Astern","Aft"]},"ABALONE":{"MEANINGS":{"1":["Noun","any of various large edible marine gastropods of the genus Haliotis having an ear-shaped shell with pearly interior",["Gastropod","Univalve"],[]]},"SYNONYMS":["Abalone","Ear-shell"]},"ABALONES":{"MEANINGS":{},"SYNONYMS":["Abalone","Ear-shell"]},"ABAMP":{"MEANINGS":{},"SYNONYMS":["Abampere","Abamp"]},"ABAMPERE":{"MEANINGS":{"1":["Noun","a unit of current equal to 10 amperes",["Current unit"],[]]},"SYNONYMS":["Abampere","Abamp"]},"ABAMPERES":{"MEANINGS":{},"SYNONYMS":["Abampere","Abamp"]},"ABAMPS":{"MEANINGS":{},"SYNONYMS":["Abampere","Abamp"]},"ABANDON":{"MEANINGS":{"1":["Verb","forsake, leave behind",["Discard","Fling","Toss","Toss out","Toss away","Chuck out","Cast aside","Dispose","Throw out","Cast out","Throw away","Cast away","Put away"],["We abandoned the old car in the empty parking lot"]],"2":["Verb","give up with the intent of never claiming again",[],["Abandon your life to God","She gave up her children to her ex-husband when she moved to Tahiti","We gave the drowning victim up for dead"]],"4":["Verb","stop maintaining or insisting on; of ideas or claims",[],["He abandoned the thought of asking for her hand in marriage","Both sides have to give up some claims in these negotiations"]],"5":["Verb","leave someone who needs or counts on you; leave in the lurch",["Leave"],["The mother deserted her children"]]},"SYNONYMS":["Abandon","Desolate","Vacate","Desert","Wantonness"]},"ABANDONED":{"MEANINGS":{"1":["Adjective","forsaken by owner or inhabitants",[],["weed-grown yard of an abandoned farmhouse"]],"2":["Adjective","free from constraint",[],["an abandoned sadness born of grief\"- Liam O'Flaherty"]]},"SYNONYMS":["Abandon","Desolate","Vacate","Desert","Abandoned"]},"ABANDONING":{"MEANINGS":{},"SYNONYMS":["Abandon","Desolate","Vacate","Desert","Forsake"]},"ABANDONMENT":{"MEANINGS":{"1":["Noun","the act of giving something up",["Rejection"],[]],"3":["Noun","the voluntary surrender of property (or a right to property) without attempting to reclaim it or give it away",["Disposal","Disposition"],[]]},"SYNONYMS":["Forsaking","Defection","Desertion","Abandonment"]},"ABANDONMENTS":{"MEANINGS":{},"SYNONYMS":["Forsaking","Defection","Desertion","Abandonment"]},"ABANDONS":{"MEANINGS":{},"SYNONYMS":["Abandon","Desolate","Vacate","Desert","Wantonness"]},"ABARTICULATION":{"MEANINGS":{"1":["Noun","dislocation of a joint",["Dislocation"],[]]},"SYNONYMS":["Abarticulation"]},"ABASE":{"MEANINGS":{},"SYNONYMS":["Humiliate","Chagrin","Abase","Mortify","Humble"]},"ABASED":{"MEANINGS":{},"SYNONYMS":["Humiliate","Chagrin","Abase","Mortify","Humble"]},"ABASEMENT":{"MEANINGS":{"1":["Noun","a low or downcast state",["Humiliation"],["each confession brought her into an attitude of abasement\"- H.L.Menchken"]]},"SYNONYMS":["Degradation","Abjection","Humiliation","Abasement"]},"ABASEMENTS":{"MEANINGS":{},"SYNONYMS":["Degradation","Abjection","Humiliation","Abasement"]},"ABASES":{"MEANINGS":{},"SYNONYMS":["Humiliate","Chagrin","Aba","Abase","Mortify"]},"ABASH":{"MEANINGS":{},"SYNONYMS":["Abash","Embarrass"]},"ABASHED":{"MEANINGS":{"1":["Adjective","feeling or caused to feel uneasy and self-conscious",[],["felt abashed at the extravagant praise","chagrined at the poor sales of his book","was embarrassed by her child's tantrums"]]},"SYNONYMS":["Abashed","Chagrined","Abash","Embarrass","Embarrassed"]},"ABASHES":{"MEANINGS":{},"SYNONYMS":["Abash","Embarrass"]},"ABASHING":{"MEANINGS":{},"SYNONYMS":["Abash","Embarrass"]},"ABASHMENT":{"MEANINGS":{"1":["Noun","feeling embarrassed due to modesty",["Embarrassment"],[]]},"SYNONYMS":["Bashfulness","Abashment"]},"ABASHMENTS":{"MEANINGS":{},"SYNONYMS":["Bashfulness","Abashment"]},"ABASIA":{"MEANINGS":{"1":["Noun","inability to walk",["Disability of walking"],[]]},"SYNONYMS":["Abasia"]},"ABASIAS":{"MEANINGS":{},"SYNONYMS":["Abasia"]},"ABASIC":{"MEANINGS":{"1":["Adjective","of or relating to abasia (inability to walk)",[],[]]},"SYNONYMS":["Abatic","Abasic"]},"ABASING":{"MEANINGS":{},"SYNONYMS":["Humiliate","Chagrin","Abase","Mortify","Humble"]},"ABATABLE":{"MEANINGS":{"1":["Adjective","capable of being abated",[],[]]},"SYNONYMS":["Abatable"]},"ABATE":{"MEANINGS":{"2":["Verb","become less in amount or intensity",["Decrease","Diminish","Lessen","Fall"],["The storm abated","The rain let up after a few hours"]]},"SYNONYMS":["Slack off","Slack","Abate","Die away","Slake"]},"ABATED":{"MEANINGS":{},"SYNONYMS":["Slack off","Slack","Abate","Die away","Slake"]},"ABATEMENT":{"MEANINGS":{"2":["Noun","the act of abating",["Moderation","Mitigation"],["laws enforcing noise abatement"]]},"SYNONYMS":["Abatement","Suspension","Reprieve","Hiatus","Respite"]},"ABATEMENTS":{"MEANINGS":{},"SYNONYMS":["Abatement","Suspension","Reprieve","Hiatus","Respite"]},"ABATES":{"MEANINGS":{},"SYNONYMS":["Slack off","Slack","Abate","Die away","Slake"]},"ABATIC":{"MEANINGS":{},"SYNONYMS":["Abatic","Abasic"]},"ABATING":{"MEANINGS":{},"SYNONYMS":["Slack off","Slack","Abate","Die away","Slake"]},"ABATIS":{"MEANINGS":{},"SYNONYMS":["Abattis","Abatis"]},"ABATISES":{"MEANINGS":{},"SYNONYMS":["Abattis","Abatis"]},"ABATOR":{"MEANINGS":{"1":["Noun","a person who abates a nuisance",["Person","Individual","Someone","Somebody","Mortal","Soul"],[]]},"SYNONYMS":["Abator"]},"ABATORS":{"MEANINGS":{},"SYNONYMS":["Abator"]},"ABATTIS":{"MEANINGS":{"1":["Noun","a line of defense consisting of a barrier of felled or live trees with branches (sharpened or with barbed wire entwined) pointed toward the enemy",["Line of defense","Line of defence"],[]]},"SYNONYMS":["Abattis","Abatis"]},"ABATTISES":{"MEANINGS":{},"SYNONYMS":["Abattis","Abatis"]},"ABATTOIR":{"MEANINGS":{"1":["Noun","a building where animals are butchered",["Building","Edifice"],[]]},"SYNONYMS":["Shambles","Butchery","Abattoir","Slaughterhouse"]},"ABATTOIRS":{"MEANINGS":{},"SYNONYMS":["Shambles","Butchery","Abattoir","Slaughterhouse"]},"ABAXIAL":{"MEANINGS":{"1":["Adjective","facing away from the axis of an organ or organism",[],["the abaxial surface of a leaf is the underside or side facing away from the stem"]]},"ANTONYMS":["adaxial"],"SYNONYMS":["Dorsal","Abaxial"]},"ABBACY":{"MEANINGS":{"1":["Noun","the jurisdiction or office of an abbot",["Jurisdiction"],[]]},"SYNONYMS":["Abbacy"]},"ABBACIES":{"MEANINGS":{},"SYNONYMS":["Abbacy"]},"ABBATIAL":{"MEANINGS":{"1":["Adjective","of or having to do with or belonging to an abbey or abbot, or abbess",[],[]]},"SYNONYMS":["Abbatial"]},"ABBE":{"MEANINGS":{"1":["Noun","a French abbot",["Abbot","Archimandrite"],[]]},"SYNONYMS":["Abbe"]},"ABBEY":{"MEANINGS":{"1":["Noun","a church associated with a monastery or convent",["Church","Church building"],[]],"2":["Noun","a convent ruled by an abbess",["Convent"],[]],"3":["Noun","a monastery ruled by an abbot",["Monastery"],[]]},"SYNONYMS":["Abbey"]},"ABBEYS":{"MEANINGS":{},"SYNONYMS":["Abbey"]},"ABBES":{"MEANINGS":{},"SYNONYMS":["Abbe"]},"ABBESS":{"MEANINGS":{"1":["Noun","the superior of a group of nuns",["Superior"],[]]},"SYNONYMS":["Prioress","Mother superior","Abbess"]},"ABBESSES":{"MEANINGS":{},"SYNONYMS":["Prioress","Mother superior","Abbess"]},"ABBOT":{"MEANINGS":{"1":["Noun","the superior of an abbey of monks",["Superior"],[]]},"SYNONYMS":["Abbot","Archimandrite"]},"ABBOTS":{"MEANINGS":{},"SYNONYMS":["Abbot","Archimandrite"]},"ABBREVIATE":{"MEANINGS":{"2":["Verb","shorten",["Reduce"],["Abbreviate `New York' and write `NY'"]]},"ANTONYMS":["expand"],"SYNONYMS":["Shorten","Foreshorten","Reduce","Cut","Abbreviate"]},"ABBREVIATED":{"MEANINGS":{"1":["Adjective","(of clothing) very short",[],["an abbreviated swimsuit","a brief bikini"]],"2":["Adjective","cut short in duration",[],["the abbreviated speech","her shortened life was clearly the result of smoking","an unsatisfactory truncated conversation"]]},"ANTONYMS":["expand"],"SYNONYMS":["Shorten","Foreshorten","Reduce","Abbreviated","Cut"]},"ABBREVIATES":{"MEANINGS":{},"ANTONYMS":["expand"],"SYNONYMS":["Shorten","Foreshorten","Reduce","Cut","Abbreviate"]},"ABBREVIATING":{"MEANINGS":{},"ANTONYMS":["expand"],"SYNONYMS":["Shorten","Foreshorten","Reduce","Cut","Abbreviate"]},"ABBREVIATION":{"MEANINGS":{"1":["Noun","a shortened form of a word or phrase",["Form","Word form","Signifier","Descriptor"],[]],"2":["Noun","shortening something by omitting parts of it",["Shortening"],[]]},"SYNONYMS":["Abbreviation"]},"ABBREVIATIONS":{"MEANINGS":{},"SYNONYMS":["Abbreviation"]},"ABBREVIATOR":{"MEANINGS":{},"SYNONYMS":["Abbreviator","Abridger"]},"ABBREVIATORS":{"MEANINGS":{},"SYNONYMS":["Abbreviator","Abridger"]},"ABCOULOMB":{"MEANINGS":{"1":["Noun","a unit of electrical charge equal to 10 coulombs",["Charge unit","Quantity unit"],[]]},"SYNONYMS":["Abcoulomb"]},"ABDICABLE":{"MEANINGS":{"1":["Adjective","capable of being discarded or renounced or relinquished",[],["abdicable responsibilites"]]},"SYNONYMS":["Abdicable"]},"ABDICATE":{"MEANINGS":{"1":["Verb","give up, such as power, as of monarchs and emperors, or duties and obligations",["Vacate","Resign","Renounce","Give up"],["The King abdicated when he married a divorcee"]]},"SYNONYMS":["Renounce","Abdicate"]},"ABDICATED":{"MEANINGS":{},"SYNONYMS":["Renounce","Abdicate"]},"ABDICATES":{"MEANINGS":{},"SYNONYMS":["Renounce","Abdicate"]},"ABDICATING":{"MEANINGS":{},"SYNONYMS":["Renounce","Abdicate"]},"ABDICATION":{"MEANINGS":{"1":["Noun","a formal resignation and renunciation of powers",["Resignation"],[]],"2":["Noun","the act of abdicating",["Resignation"],[]]},"SYNONYMS":["Stepping down","Abdication"]},"ABDICATIONS":{"MEANINGS":{},"SYNONYMS":["Stepping down","Abdication"]},"ABDICATOR":{"MEANINGS":{"1":["Noun","one who formally relinquishes an office or responsibility",["Quitter"],[]]},"SYNONYMS":["Abdicator"]},"ABDOMEN":{"MEANINGS":{"1":["Noun","the region of the body of a vertebrate between the thorax and the pelvis",["Body part"],[]]},"SYNONYMS":["Stomach","Belly","Abdomen","Venter","Abdominal cavity"]},"ABDOMENS":{"MEANINGS":{},"SYNONYMS":["Stomach","Belly","Abdomen","Venter","Abdominal cavity"]},"ABDOMINAL":{"MEANINGS":{"1":["Adjective","of or relating to or near the abdomen",[],["abdominal muscles"]]},"SYNONYMS":["Abdominal muscle","Ab","Abdominal"]},"ABDOMINALS":{"MEANINGS":{},"SYNONYMS":["Abdominal muscle","Ab","Abdominal"]},"ABDOMINOCENTESIS":{"MEANINGS":{"1":["Noun","centesis of the belly to remove fluid for diagnosis",["Centesis"],[]]},"SYNONYMS":["Abdominocentesis","Paracentesis"]},"ABDOMINOUS":{"MEANINGS":{"1":["Adjective","having a large belly",[],[]]},"SYNONYMS":["Paunchy","Potbellied","Abdominous"]},"ABDOMINOVESICAL":{"MEANINGS":{"1":["Adjective","of or relating to the abdomen and the urinary bladder",[],[]]},"SYNONYMS":["Abdominovesical"]},"ABDUCE":{"MEANINGS":{},"SYNONYMS":["Abduce","Adduce","Cite"]},"ABDUCED":{"MEANINGS":{},"SYNONYMS":["Abduce","Adduce","Cite"]},"ABDUCENS":{"MEANINGS":{},"SYNONYMS":["Abducent nerve","Abducens","Sixth cranial nerve","Nervus abducens","Abducent"]},"ABDUCENT":{"MEANINGS":{"1":["Adjective","especially of muscles; drawing away from the midline of the body or from an adjacent part",[],[]]},"ANTONYMS":["adducent"],"SYNONYMS":["Abducting","Abducent nerve","Abducens","Sixth cranial nerve","Nervus abducens"]},"ABDUCES":{"MEANINGS":{},"SYNONYMS":["Abduce","Adduce","Cite"]},"ABDUCING":{"MEANINGS":{},"SYNONYMS":["Abduce","Adduce","Cite"]},"ABDUCT":{"MEANINGS":{"2":["Verb","pull away from the body",["Pull","Draw","Force"],["this muscle abducts"]]},"ANTONYMS":["adduct"],"SYNONYMS":["Kidnap","Snatch","Abduct","Nobble"]},"ABDUCTED":{"MEANINGS":{},"ANTONYMS":["adduct"],"SYNONYMS":["Kidnap","Snatch","Abduct","Nobble"]},"ABDUCTING":{"MEANINGS":{},"ANTONYMS":["adducent","adduct"],"SYNONYMS":["Abducting","Kidnap","Abduct","Nobble","Snatch"]},"ABDUCTION":{"MEANINGS":{"1":["Noun","the criminal act of capturing and carrying away by force a family member; if a man's wife is abducted it is a crime against the family relationship and against the wife",["Capture","Seizure"],[]],"2":["Noun","(physiology) moving of a body part away from the central axis of the body",["Motion","Movement","Move","Motility"],[]]},"SYNONYMS":["Abduction"]},"ABDUCTIONS":{"MEANINGS":{},"SYNONYMS":["Abduction"]},"ABDUCTOR":{"MEANINGS":{"2":["Noun","a muscle that draws a body part away from the median line",["Skeletal muscle","Striated muscle"],[]]},"SYNONYMS":["Kidnapper","Abductor muscle","Snatcher","Abductor","Kidnaper"]},"ABDUCTORS":{"MEANINGS":{},"SYNONYMS":["Kidnapper","Abductor muscle","Snatcher","Abductor","Kidnaper"]},"ABDUCTS":{"MEANINGS":{},"ANTONYMS":["adduct"],"SYNONYMS":["Kidnap","Snatch","Abduct","Nobble"]},"ABEAM":{"MEANINGS":{"1":["Adverb","at right angles to the length of a ship or airplane",[],[]]},"SYNONYMS":["Abeam"]},"ABECEDARIAN":{"MEANINGS":{"1":["Adjective","alphabetically arranged (as for beginning readers)",[],[]],"2":["Noun","a 16th century sect of Anabaptists centered in Germany who had an absolute disdain for human knowledge",["Sect","Religious sect","Religious order"],[]]},"SYNONYMS":["Abecedarian"]},"ABECEDARIANS":{"MEANINGS":{},"SYNONYMS":["Abecedarian"]},"ABECEDARIUS":{"MEANINGS":{"1":["Noun","a poem having lines beginning with letters of the alphabet in regular order",["Poem","Verse form"],[]]},"SYNONYMS":["Abecedarius"]},"ABED":{"MEANINGS":{"1":["Adverb","in bed",[],[]]},"SYNONYMS":["Abed"]},"ABEYANCE":{"MEANINGS":{"1":["Noun","temporary cessation or suspension",["Inaction","Inactivity","Inactiveness"],[]]},"SYNONYMS":["Suspension","Abeyance"]},"ABEYANCES":{"MEANINGS":{},"SYNONYMS":["Suspension","Abeyance"]},"ABEYANT":{"MEANINGS":{"1":["Adjective","inactive but capable of becoming active",[],["her feelings of affection are dormant but easily awakened"]]},"SYNONYMS":["Abeyant","Dormant"]},"ABELIA":{"MEANINGS":{"1":["Noun","any of various deciduous or evergreen ornamental shrubs of the genus Abelia having opposite simple leaves and cymes of small white or pink or purplish flowers; Asia and Mexico",["Shrub","Bush"],[]]},"SYNONYMS":["Abelia"]},"ABELMOSCHUS":{"MEANINGS":{"1":["Noun","genus of tropical coarse herbs having large lobed leaves and often yellow flowers",["Dilleniid dicot genus"],[]]},"SYNONYMS":["Genus abelmoschus","Abelmoschus"]},"ABELMOSK":{"MEANINGS":{"1":["Noun","bushy herb of tropical Asia grown for its yellow or pink to scarlet blooms that resemble the hibiscus",["Mallow"],[]]},"SYNONYMS":["Hibiscus moschatus","Abelmosk","Abelmoschus moschatus","Musk mallow"]},"ABELMOSKS":{"MEANINGS":{},"SYNONYMS":["Hibiscus moschatus","Abelmosk","Abelmoschus moschatus","Musk mallow"]},"ABERRANCE":{"MEANINGS":{"1":["Noun","a state or condition markedly different from the norm",["Abnormality","Abnormalcy"],[]]},"SYNONYMS":["Aberration","Aberrancy","Deviance","Aberrance"]},"ABERRANCY":{"MEANINGS":{},"SYNONYMS":["Aberration","Aberrancy","Deviance","Aberrance"]},"ABERRANCIES":{"MEANINGS":{},"SYNONYMS":["Aberration","Aberrancy","Deviance","Aberrance"]},"ABERRANT":{"MEANINGS":{"1":["Adjective","markedly different from an accepted norm",[],["aberrant behavior","deviant ideas"]]},"SYNONYMS":["Deviate","Aberrant","Deviant"]},"ABERRANTS":{"MEANINGS":{},"SYNONYMS":["Aberrant"]},"ABERRATE":{"MEANINGS":{"1":["Verb","diverge from the expected",["Deviate","Vary","Diverge","Depart"],["The President aberrated from being a perfect gentleman"]],"2":["Verb","diverge or deviate from the straight path; produce aberration",["Deviate","Vary","Diverge","Depart"],["The surfaces of the concave lens may be proportioned so as to aberrate exactly equal to the convex lens"]]},"SYNONYMS":["Aberrate"]},"ABERRATED":{"MEANINGS":{},"SYNONYMS":["Aberrate"]},"ABERRATING":{"MEANINGS":{},"SYNONYMS":["Aberrate"]},"ABERRATION":{"MEANINGS":{"2":["Noun","a disorder in one's mental state",["Mental disorder","Mental disturbance","Disturbance","Psychological disorder","Folie"],[]],"3":["Noun","an optical phenomenon resulting from the failure of a lens or mirror to produce a good image",["Optical phenomenon"],[]]},"SYNONYMS":["Aberrancy","Deviance","Distortion","Optical aberration","Aberration"]},"ABERRATIONS":{"MEANINGS":{},"SYNONYMS":["Aberrancy","Deviance","Distortion","Optical aberration","Aberration"]},"ABET":{"MEANINGS":{"1":["Verb","assist or encourage, usually in some wrongdoing",["Assist"],[]]},"SYNONYMS":["Abet"]},"ABETMENT":{"MEANINGS":{"1":["Noun","the verbal act of urging on",["Encouragement"],[]]},"SYNONYMS":["Abettal","Instigation","Abetment"]},"ABETMENTS":{"MEANINGS":{},"SYNONYMS":["Abettal","Instigation","Abetment"]},"ABETS":{"MEANINGS":{},"SYNONYMS":["Abet"]},"ABETTAL":{"MEANINGS":{},"SYNONYMS":["Abettal","Instigation","Abetment"]},"ABETTALS":{"MEANINGS":{},"SYNONYMS":["Abettal","Instigation","Abetment"]},"ABETTED":{"MEANINGS":{},"SYNONYMS":["Abet"]},"ABETTER":{"MEANINGS":{},"SYNONYMS":["Abetter","Abettor"]},"ABETTERS":{"MEANINGS":{},"SYNONYMS":["Abetter","Abettor"]},"ABETTING":{"MEANINGS":{},"SYNONYMS":["Abet"]},"ABETTOR":{"MEANINGS":{"1":["Noun","one who helps or encourages or incites another",["Accessory","Accessary"],[]]},"SYNONYMS":["Abetter","Abettor"]},"ABETTORS":{"MEANINGS":{},"SYNONYMS":["Abetter","Abettor"]},"ABFARAD":{"MEANINGS":{"1":["Noun","a capacitance unit equal to one billion farads",["Capacitance unit"],[]]},"SYNONYMS":["Abfarad"]},"ABFARADS":{"MEANINGS":{},"SYNONYMS":["Abfarad"]},"ABHENRY":{"MEANINGS":{"1":["Noun","a unit of inductance equal to one billionth of a henry",["Inductance unit"],[]]},"SYNONYMS":["Abhenry"]},"ABHENRIES":{"MEANINGS":{},"SYNONYMS":["Abhenry"]},"ABHENRYS":{"MEANINGS":{},"SYNONYMS":["Abhenry"]},"ABHOR":{"MEANINGS":{"1":["Verb","find repugnant",["Hate","Detest"],["I loathe that man","She abhors cats"]]},"SYNONYMS":["Abominate","Execrate","Loathe","Abhor"]},"ABHORRED":{"MEANINGS":{},"SYNONYMS":["Abominate","Execrate","Loathe","Abhor"]},"ABHORRENCE":{"MEANINGS":{"1":["Noun","hate coupled with disgust",["Disgust","Hate","Hatred"],[]]},"SYNONYMS":["Abomination","Execration","Abhorrence","Loathing","Detestation"]},"ABHORRENCES":{"MEANINGS":{},"SYNONYMS":["Abomination","Execration","Abhorrence","Loathing","Detestation"]},"ABHORRENT":{"MEANINGS":{"1":["Adjective","offensive to the mind",[],["an abhorrent deed","the obscene massacre at Wounded Knee","morally repugnant customs","repulsive behavior","the most repulsive character in recent novels"]]},"SYNONYMS":["Repulsive","Abhorrent","Repugnant","Obscene","Detestable"]},"ABHORRER":{"MEANINGS":{"1":["Noun","a signer of a 1679 address to Charles II in which those who petitioned for the reconvening of parliament were condemned and abhorred",["Signer","Signatory"],[]]},"SYNONYMS":["Abhorrer"]},"ABHORRERS":{"MEANINGS":{},"SYNONYMS":["Abhorrer"]},"ABHORRING":{"MEANINGS":{},"SYNONYMS":["Abominate","Execrate","Loathe","Abhor"]},"ABHORS":{"MEANINGS":{},"SYNONYMS":["Abominate","Execrate","Loathe","Abhor"]},"ABIDANCE":{"MEANINGS":{"3":["Noun","the act of abiding (enduring without yielding)",["Continuance","Continuation"],[]]},"ANTONYMS":["nonconformity","noncompliance"],"SYNONYMS":["Conformation","Residence","Residency","Conformity","Abidance"]},"ABIDANCES":{"MEANINGS":{},"ANTONYMS":["nonconformity","noncompliance"],"SYNONYMS":["Conformation","Residence","Residency","Conformity","Abidance"]},"ABIDE":{"MEANINGS":{},"SYNONYMS":["Digest","Stomach","Brook","Endure","Support"]},"ABIDED":{"MEANINGS":{},"SYNONYMS":["Digest","Stomach","Brook","Endure","Support"]},"ABIDES":{"MEANINGS":{},"SYNONYMS":["Digest","Stomach","Brook","Endure","Support"]},"ABIDING":{"MEANINGS":{"1":["Adjective","unceasing",[],["an abiding belief","imperishable truths"]]},"SYNONYMS":["Digest","Stomach","Brook","Endure","Support"]},"ABIENCE":{"MEANINGS":{"1":["Noun","(psychology) an urge to withdraw or avoid a situation or an object",["Urge","Impulse"],[]]},"ANTONYMS":["adience"],"SYNONYMS":["Abience"]},"ABIENT":{"MEANINGS":{"1":["Adjective","characterized by avoidance or withdrawal",[],[]]},"ANTONYMS":["adient"],"SYNONYMS":["Abient"]},"ABILITY":{"MEANINGS":{"1":["Noun","the quality of being able to perform; a quality that permits or facilitates achievement or accomplishment",["Quality"],[]],"2":["Noun","possession of the qualities (especially mental qualities) required to do something or get something done",["Cognition","Knowledge","Noesis"],["danger heightened his powers of discrimination"]]},"ANTONYMS":["inability"],"SYNONYMS":["Ability","Power"]},"ABILITIES":{"MEANINGS":{},"ANTONYMS":["inability"],"SYNONYMS":["Ability","Power"]},"ABIOGENESIS":{"MEANINGS":{"1":["Noun","a hypothetical organic phenomenon by which living organisms are created from nonliving matter",["Organic phenomenon"],[]]},"SYNONYMS":["Spontaneous generation","Autogeny","Autogenesis","Abiogenesis"]},"ABIOGENETIC":{"MEANINGS":{"1":["Adjective","originating by abiogenesis",[],[]]},"SYNONYMS":["Abiogenetic"]},"ABIOGENIST":{"MEANINGS":{"1":["Noun","a believer in abiogenesis",["Believer","Truster"],[]]},"SYNONYMS":["Abiogenist"]},"ABIOTROPHY":{"MEANINGS":{"1":["Noun","a loss of vitality and a degeneration of cells and tissues not due to any apparent injury",["Degeneration","Retrogression"],[]]},"SYNONYMS":["Abiotrophy"]},"ABYSM":{"MEANINGS":{},"SYNONYMS":["Abysm","Abyss"]},"ABYSMAL":{"MEANINGS":{"1":["Adjective","very great; limitless",[],["abysmal misery","abysmal stupidity"]],"2":["Adjective","resembling an abyss in depth; so deep as to be unmeasurable",[],["the abyssal depths of the ocean"]]},"SYNONYMS":["Unfathomable","Abysmal","Abyssal"]},"ABYSMALLY":{"MEANINGS":{},"SYNONYMS":["Abominably","Atrociously","Rottenly","Abysmally","Awfully"]},"ABYSMS":{"MEANINGS":{},"SYNONYMS":["Abysm","Abyss"]},"ABYSS":{"MEANINGS":{"1":["Noun","a bottomless gulf or pit; any unfathomable (or apparently unfathomable) cavity or chasm or void extending below (often used figuratively)",["Chasm"],[]]},"SYNONYMS":["Abysm","Abyss","Abye","Expiate","Aby"]},"ABYSSAL":{"MEANINGS":{"1":["Adjective","relating to ocean depths from 2000 to 5000 meters",[],[]]},"SYNONYMS":["Unfathomable","Abysmal","Abyssal"]},"ABYSSES":{"MEANINGS":{},"SYNONYMS":["Abysm","Abyss","Abye","Expiate","Aby"]},"ABYSSINIA":{"MEANINGS":{},"SYNONYMS":["Federal democratic republic of ethiopia","Yaltopya","Ethiopia","Abyssinia"]},"ABYSSINIAN":{"MEANINGS":{"1":["Noun","a small slender short-haired breed of African origin having brownish fur with a reddish undercoat",["Domestic cat","House cat","Felis domesticus","Felis catus"],[]]},"SYNONYMS":["Abyssinian cat","Abyssinian"]},"ABYSSINIANS":{"MEANINGS":{},"SYNONYMS":["Abyssinian cat","Abyssinian"]},"ABJECT":{"MEANINGS":{"1":["Adjective","of the most contemptible kind",[],["abject cowardice","a low stunt to pull","a low-down sneak","his miserable treatment of his family","You miserable skunk!","a scummy rabble","a scurvy trick"]],"2":["Adjective","most unfortunate or miserable",[],["the most abject slaves joined in the revolt","abject poverty"]],"3":["Adjective","showing utter resignation or hopelessness",[],["abject surrender"]],"4":["Adjective","showing humiliation or submissiveness",[],["an abject apology"]]},"SYNONYMS":["Miserable","Scummy","Low-down","Scurvy","Low"]},"ABJECTION":{"MEANINGS":{},"SYNONYMS":["Degradation","Abjection","Abasement"]},"ABJECTIONS":{"MEANINGS":{},"SYNONYMS":["Degradation","Abjection","Abasement"]},"ABJECTLY":{"MEANINGS":{"1":["Adverb","in a hopeless resigned manner",[],["she shrugged her shoulders abjectly"]]},"SYNONYMS":["Resignedly","Abjectly"]},"ABJURATION":{"MEANINGS":{},"SYNONYMS":["Recantation","Abjuration","Retraction"]},"ABJURATIONS":{"MEANINGS":{},"SYNONYMS":["Recantation","Abjuration","Retraction"]},"ABJURE":{"MEANINGS":{"1":["Verb","formally reject or disavow a formerly held belief, usually under pressure",["Disown","Renounce","Repudiate"],["He retracted his earlier statements about his religion","She abjured her beliefs"]]},"SYNONYMS":["Resile","Abjure","Forswear","Recant","Retract"]},"ABJURED":{"MEANINGS":{},"SYNONYMS":["Resile","Abjure","Forswear","Recant","Retract"]},"ABJURER":{"MEANINGS":{"1":["Noun","a person who abjures",["Person","Individual","Someone","Somebody","Mortal","Soul"],[]]},"SYNONYMS":["Abjurer"]},"ABJURERS":{"MEANINGS":{},"SYNONYMS":["Abjurer"]},"ABJURES":{"MEANINGS":{},"SYNONYMS":["Resile","Abjure","Forswear","Recant","Retract"]},"ABJURING":{"MEANINGS":{},"SYNONYMS":["Resile","Abjure","Forswear","Recant","Retract"]},"ABKHAS":{"MEANINGS":{},"SYNONYMS":["Abkhazian","Abkhas","Abkhaz","Abkhasian"]},"ABKHAZIAN":{"MEANINGS":{"2":["Noun","a Circassian language spoken by the Abkhaz",["Circassian"],[]]},"SYNONYMS":["Abkhazian","Abkhas","Abkhaz","Abkhasian"]},"ABLACTATE":{"MEANINGS":{},"SYNONYMS":["Ablactate","Wean"]},"ABLACTATED":{"MEANINGS":{},"SYNONYMS":["Ablactate","Wean"]},"ABLACTATING":{"MEANINGS":{},"SYNONYMS":["Ablactate","Wean"]},"ABLACTATION":{"MEANINGS":{"1":["Noun","the cessation of lactation",["Bodily process","Body process","Bodily function","Activity"],[]]},"SYNONYMS":["Weaning","Ablactation"]},"ABLATE":{"MEANINGS":{"1":["Verb","wear away through erosion or vaporization",["Wear","Wear off","Wear out","Wear down","Wear thin"],[]],"2":["Verb","remove an organ or bodily structure",["Remove","Take","Take away","Withdraw"],[]]},"SYNONYMS":["Ablate"]},"ABLATED":{"MEANINGS":{"1":["Adjective","made smaller or less by melting or erosion or vaporization",[],["the rocket's ablated head shield"]]},"SYNONYMS":["Ablate","Ablated"]},"ABLATES":{"MEANINGS":{},"SYNONYMS":["Ablate"]},"ABLATING":{"MEANINGS":{},"SYNONYMS":["Ablate"]},"ABLATION":{"MEANINGS":{"1":["Noun","surgical removal of a body part or tissue",["Operation","Surgery","Surgical operation","Surgical procedure","Surgical process"],[]],"2":["Noun","the erosive process that reduces the size of glaciers",["Erosion","Eroding","Eating away","Wearing","Wearing away"],[]]},"SYNONYMS":["Excision","Extirpation","Ablation","Cutting out"]},"ABLATIONS":{"MEANINGS":{},"SYNONYMS":["Excision","Extirpation","Ablation","Cutting out"]},"ABLATIVE":{"MEANINGS":{"1":["Adjective","relating to the ablative case",[],[]],"2":["Adjective","tending to ablate; i.e. to be removed or vaporized at very high temperature",[],["ablative material on a rocket cone"]]},"SYNONYMS":["Ablative","Ablative case"]},"ABLATIVES":{"MEANINGS":{},"SYNONYMS":["Ablative","Ablative case"]},"ABLAUT":{"MEANINGS":{"1":["Noun","a vowel whose quality or length is changed to indicate linguistic distinctions (such as sing sang sung song)",["Vowel","Vowel sound"],[]]},"SYNONYMS":["Ablaut"]},"ABLAUTS":{"MEANINGS":{},"SYNONYMS":["Ablaut"]},"ABLAZE":{"MEANINGS":{"1":["Adjective","keenly excited (especially sexually) or indicating excitement",[],["his face all ablaze with excitement\"- Bram Stoker","he was aflame with desire"]],"2":["Adjective","lighted up by or as by fire or flame",[],["forests set ablaze (or afire) by lightning","even the car's tires were aflame","a night aflare with fireworks","candles alight on the tables","houses on fire"]],"3":["Adjective","resembling flame in brilliance or color",[],["maple trees ablaze in autumn"]],"4":["Adjective","lighted with red light as if with flames",[],["streets ablaze with lighted Christmas trees","the inflamed clouds at sunset","reddened faces around the campfire"]]},"SYNONYMS":["On fire","Aroused","Ablaze","Alight","Inflamed"]},"ABLE":{"MEANINGS":{"1":["Adjective","(usually followed by `to') having the necessary means or skill or know-how or authority to do something",[],["able to swim","she was able to program her computer","we were at last able to buy a car","able to get a grant for the project"]],"2":["Adjective","have the skills and qualifications to do things well",[],["able teachers","a capable administrator","children as young as 14 can be extremely capable and dependable"]],"3":["Adjective","having inherent physical or mental ability or capacity",[],["able to learn","human beings are able to walk on two feet","Superman is able to leap tall buildings"]],"4":["Adjective","having a strong healthy body",[],["an able seaman","every able-bodied young man served in the army"]]},"ANTONYMS":["unable"],"SYNONYMS":["Capable","Able","Able-bodied"]},"ABLEPHARIA":{"MEANINGS":{"1":["Noun","a congenital absence of eyelids (partial or complete)",["Birth defect","Congenital anomaly","Congenital defect","Congenital disorder","Congenital abnormality"],[]]},"SYNONYMS":["Ablepharia"]},"ABLER":{"MEANINGS":{},"ANTONYMS":["unable"],"SYNONYMS":["Capable","Able","Able-bodied"]},"ABLEST":{"MEANINGS":{},"ANTONYMS":["unable"],"SYNONYMS":["Capable","Able","Able-bodied"]},"ABLY":{"MEANINGS":{},"ANTONYMS":["incompetently"],"SYNONYMS":["Ably","Aptly","Capably","Competently"]},"ABLOOM":{"MEANINGS":{"1":["Adjective","bursting into flower",[],["flowering spring trees"]]},"SYNONYMS":["Abloom","Efflorescent"]},"ABLUTION":{"MEANINGS":{"1":["Noun","the ritual washing of a priest's hands or of sacred vessels",["Ritual","Wash","Washing","Lavation"],[]]},"SYNONYMS":["Ablution"]},"ABLUTIONARY":{"MEANINGS":{"1":["Adjective","cleansing the body by washing; especially ritual washing of e.g. hands",[],["ablutionary rituals"]]},"SYNONYMS":["Ablutionary","Cleansing"]},"ABLUTIONS":{"MEANINGS":{},"SYNONYMS":["Ablution"]},"ABNAKI":{"MEANINGS":{"1":["Adjective","of or relating to the Abnakis or their language",[],[]],"2":["Noun","the Algonquian language spoken by the Abnaki and Penobscot",["Algonquian","Algonquin","Algonquian language"],[]]},"SYNONYMS":["Abenaki","Abnaki"]},"ABNEGATE":{"MEANINGS":{"2":["Verb","surrender (power or a position)",["Surrender","Give up"],["The King abnegated his power to the ministers"]],"3":["Verb","deny or renounce",["Deny"],["They abnegated their gods"]]},"SYNONYMS":["Abnegate","Deny"]},"ABNEGATED":{"MEANINGS":{},"SYNONYMS":["Abnegate","Deny"]},"ABNEGATES":{"MEANINGS":{},"SYNONYMS":["Abnegate","Deny"]},"ABNEGATING":{"MEANINGS":{},"SYNONYMS":["Abnegate","Deny"]},"ABNEGATION":{"MEANINGS":{"1":["Noun","the denial and rejection of a doctrine or belief",["Denial"],["abnegation of the Holy Trinity"]],"2":["Noun","renunciation of your own interests in favor of the interests of others",["Renunciation","Forgoing","Forswearing","Selflessness","Self-sacrifice"],[]]},"SYNONYMS":["Self-renunciation","Self-abnegation","Denial","Self-denial","Abnegation"]},"ABNEGATIONS":{"MEANINGS":{},"SYNONYMS":["Self-renunciation","Self-abnegation","Denial","Self-denial","Abnegation"]},"ABNEGATOR":{"MEANINGS":{"1":["Noun","one who gives up or relinquishes or renounces something",["Donor","Giver","Presenter","Bestower","Conferrer"],[]]},"SYNONYMS":["Abnegator"]},"ABNEGATORS":{"MEANINGS":{},"SYNONYMS":["Abnegator"]},"ABNORMAL":{"MEANINGS":{"1":["Adjective","not normal; not typical or usual or regular or conforming to a norm",[],["abnormal powers of concentration","abnormal amounts of rain","abnormal circumstances","an abnormal interest in food"]],"2":["Adjective","departing from the normal in e.g. intelligence and development",[],["they were heartbroken when they learned their child was abnormal","an abnormal personality"]],"3":["Adjective","much greater than the normal",[],["abnormal profits","abnormal ambition"]]},"ANTONYMS":["normal"],"SYNONYMS":["Unnatural","Abnormal"]},"ABNORMALCY":{"MEANINGS":{},"ANTONYMS":["normality"],"SYNONYMS":["Abnormalcy","Abnormality"]},"ABNORMALCIES":{"MEANINGS":{},"ANTONYMS":["normality"],"SYNONYMS":["Abnormalcy","Abnormality"]},"ABNORMALITY":{"MEANINGS":{"1":["Noun","an abnormal physical condition resulting from defective genes or developmental deficiencies",["Physical condition","Physiological state","Physiological condition"],[]],"2":["Noun","retardation sufficient to fall outside the normal range of intelligence",["Retardation","Mental retardation","Backwardness","Slowness","Subnormality"],[]],"3":["Noun","marked strangeness as a consequence of being abnormal",["Unfamiliarity","Strangeness"],[]],"4":["Noun","behavior that breaches the rule or etiquette or custom or morality",["Misbehavior","Misbehaviour","Misdeed"],[]]},"ANTONYMS":["normality"],"SYNONYMS":["Irregularity","Mental defectiveness","Abnormalcy","Freakishness","Abnormality"]},"ABNORMALITIES":{"MEANINGS":{},"ANTONYMS":["normality"],"SYNONYMS":["Irregularity","Mental defectiveness","Abnormalcy","Freakishness","Abnormality"]},"ABNORMALLY":{"MEANINGS":{"1":["Adverb","in an abnormal manner",[],["they were behaving abnormally","his blood pressure was abnormally low"]]},"SYNONYMS":["Abnormally"]},"ABOARD":{"MEANINGS":{"1":["Adverb","on a ship, train, plane or other vehicle",[],[]],"2":["Adverb","on first or second or third base",[],["Their second homer with Bob Allison aboard"]],"3":["Adverb","side by side",[],["anchored close aboard another ship"]],"4":["Adverb","part of a group",[],["Bill's been aboard for three years now"]]},"SYNONYMS":["On board","On base","Alongside","Aboard"]},"ABODE":{"MEANINGS":{},"SYNONYMS":["Digest","Home","Stand","Abide","Habitation"]},"ABODES":{"MEANINGS":{},"SYNONYMS":["Dwelling","Home","Domicile","Dwelling house","Residence"]},"ABOHM":{"MEANINGS":{"1":["Noun","a unit of resistance equal to a billionth of an ohm",["Resistance unit"],[]]},"SYNONYMS":["Abohm"]},"ABOHMS":{"MEANINGS":{},"SYNONYMS":["Abohm"]},"ABOLISH":{"MEANINGS":{"1":["Verb","do away with",[],["Slavery was abolished in the mid-19th century in America and in Russia"]]},"ANTONYMS":["establish"],"SYNONYMS":["Abolish","Get rid of"]},"ABOLISHABLE":{"MEANINGS":{"1":["Adjective","capable of being abolished",[],[]]},"SYNONYMS":["Abolishable"]},"ABOLISHED":{"MEANINGS":{},"ANTONYMS":["establish"],"SYNONYMS":["Abolish","Get rid of"]},"ABOLISHES":{"MEANINGS":{},"ANTONYMS":["establish"],"SYNONYMS":["Abolish","Get rid of"]},"ABOLISHING":{"MEANINGS":{},"ANTONYMS":["establish"],"SYNONYMS":["Abolish","Get rid of"]},"ABOLISHMENT":{"MEANINGS":{},"SYNONYMS":["Abolishment","Abolition"]},"ABOLISHMENTS":{"MEANINGS":{},"SYNONYMS":["Abolishment","Abolition"]},"ABOLITION":{"MEANINGS":{"1":["Noun","the act of abolishing a system or practice or institution (especially abolishing slavery)",["Termination","Ending","Conclusion"],["the abolition of capital punishment"]]},"SYNONYMS":["Abolishment","Abolition"]},"ABOLITIONARY":{"MEANINGS":{"1":["Adjective","relating to or favoring abolition, especially abolition of slavery",[],[]]},"SYNONYMS":["Abolitionary"]},"ABOLITIONISM":{"MEANINGS":{"1":["Noun","the doctrine that calls for the abolition of slavery",["Doctrine","Philosophy","Philosophical system","School of thought","Ism"],[]]},"SYNONYMS":["Abolitionism"]},"ABOLITIONIST":{"MEANINGS":{"1":["Noun","a reformer who favors abolishing slavery",["Reformer","Reformist","Crusader","Social reformer","Meliorist"],[]]},"SYNONYMS":["Emancipationist","Abolitionist"]},"ABOLITIONISTS":{"MEANINGS":{},"SYNONYMS":["Emancipationist","Abolitionist"]},"ABOLITIONS":{"MEANINGS":{},"SYNONYMS":["Abolishment","Abolition"]},"ABOMASAL":{"MEANINGS":{"1":["Adjective","relating to the abomasum (the fourth compartment of the stomach of ruminants)",[],[]]},"SYNONYMS":["Abomasal"]},"ABOMASUM":{"MEANINGS":{"1":["Noun","the fourth compartment of the stomach of a ruminant; the one where digestion takes place",["Stomach","Tummy","Tum","Breadbasket"],[]]},"SYNONYMS":["Abomasum","Fourth stomach"]},"ABOMINABLE":{"MEANINGS":{"1":["Adjective","unequivocally detestable",[],["abominable treatment of prisoners","detestable vices","execrable crimes","consequences odious to those you govern\"- Edmund Burke"]]},"SYNONYMS":["Odious","Atrocious","Abominable","Awful","Execrable"]},"ABOMINABLY":{"MEANINGS":{},"SYNONYMS":["Abominably","Atrociously","Detestably","Rottenly","Abysmally"]},"ABOMINATE":{"MEANINGS":{},"SYNONYMS":["Abominate","Execrate","Loathe","Abhor"]},"ABOMINATED":{"MEANINGS":{},"SYNONYMS":["Abominate","Execrate","Loathe","Abhor"]},"ABOMINATES":{"MEANINGS":{},"SYNONYMS":["Abominate","Execrate","Loathe","Abhor"]},"ABOMINATING":{"MEANINGS":{},"SYNONYMS":["Abominate","Execrate","Loathe","Abhor"]},"ABOMINATION":{"MEANINGS":{"1":["Noun","a person who is loathsome or disgusting",["Person","Individual","Someone","Somebody","Mortal","Soul"],[]],"3":["Noun","an action that is vicious or vile; an action that arouses disgust or abhorrence",["Transgression","Evildoing"],["his treatment of the children is an abomination"]]},"SYNONYMS":["Abomination","Execration","Abhorrence","Loathing","Detestation"]},"ABOMINATIONS":{"MEANINGS":{},"SYNONYMS":["Abomination","Execration","Abhorrence","Loathing","Detestation"]},"ABOMINATOR":{"MEANINGS":{"1":["Noun","one who hates or loathes",["Hater"],[]]},"SYNONYMS":["Loather","Abominator"]},"ABOMINATORS":{"MEANINGS":{},"SYNONYMS":["Loather","Abominator"]},"ABORAD":{"MEANINGS":{"1":["Adverb","away from the mouth or oral region",[],[]]},"ANTONYMS":["orad"],"SYNONYMS":["Aborad"]},"ABORAL":{"MEANINGS":{"1":["Adjective","opposite to or away from the mouth",[],["the aboral surface of a starfish"]]},"ANTONYMS":["oral"],"SYNONYMS":["Aboral"]},"ABORIGINAL":{"MEANINGS":{"1":["Adjective","of or pertaining to members of the indigenous people of Australia",[],["an Aboriginal rite"]],"3":["Adjective","having existed from the beginning; in an earliest or original stage or state",[],["aboriginal forests","primal eras before the appearance of life on earth","the forest primeval","primordial matter","primordial forms of life"]]},"ANTONYMS":["nonnative"],"SYNONYMS":["Native","Primal","Indigene","Australian aborigine","Primaeval"]},"ABORIGINALS":{"MEANINGS":{},"SYNONYMS":["Native","Indigene","Australian aborigine","Aboriginal","Abo"]},"ABORIGINE":{"MEANINGS":{"2":["Noun","a dark-skinned member of a race of people living in Australia when Europeans arrived",["Australian","Aussie","Ethnic group","Ethnos"],[]]},"SYNONYMS":["Native","Indigene","Australian aborigine","Aboriginal","Abo"]},"ABORIGINES":{"MEANINGS":{},"SYNONYMS":["Native","Indigene","Australian aborigine","Aboriginal","Abo"]},"ABORT":{"MEANINGS":{"1":["Verb","terminate before completion",["End","Terminate"],["abort the mission","abort the process running on my computer"]],"2":["Verb","cease development, die, and be aborted",["Die","Decease","Perish","Go","Exit","Pass away","Expire","Pass","Kick the bucket","Cash in one's chips","Buy the farm","Conk","Give-up the ghost","Drop dead","Pop off","Choke","Croak","Snuff it"],["an aborting fetus"]],"3":["Verb","terminate a pregnancy by undergoing an abortion",["Exhaust","Discharge","Expel","Eject","Release"],[]]},"SYNONYMS":["Abort"]},"ABORTED":{"MEANINGS":{},"SYNONYMS":["Abort"]},"ABORTICIDE":{"MEANINGS":{"2":["Noun","the act of destroying a fetus",["Induced abortion"],[]]},"SYNONYMS":["Abortion-inducing drug","Abortifacient","Feticide","Aborticide"]},"ABORTIFACIENT":{"MEANINGS":{"1":["Adjective","causing abortion",[],[]]},"SYNONYMS":["Abortion-inducing drug","Abortifacient","Aborticide"]},"ABORTING":{"MEANINGS":{},"SYNONYMS":["Abort"]},"ABORTION":{"MEANINGS":{"1":["Noun","termination of pregnancy",["Termination","Ending","Conclusion"],[]]},"SYNONYMS":["Miscarriage","Abortion"]},"ABORTIONIST":{"MEANINGS":{"1":["Noun","a person (who should be a doctor) who terminates pregnancies",["Doctor","Doc","Physician","Md","Dr.","Medico"],[]]},"SYNONYMS":["Abortionist"]},"ABORTIONISTS":{"MEANINGS":{},"SYNONYMS":["Abortionist"]},"ABORTIONS":{"MEANINGS":{},"SYNONYMS":["Miscarriage","Abortion"]},"ABORTIVE":{"MEANINGS":{"1":["Adjective","failing to accomplish an intended result",[],["an abortive revolt","a stillborn plot to assassinate the President"]]},"SYNONYMS":["Stillborn","Abortive","Unsuccessful"]},"ABORTIVELY":{"MEANINGS":{"1":["Adverb","in an unfruitful manner",[],[]]},"SYNONYMS":["Abortively"]},"ABORTS":{"MEANINGS":{},"SYNONYMS":["Abort"]},"ABORTUS":{"MEANINGS":{"1":["Noun","a human fetus whose weight is less than 0.5 kilogram when removed or expelled from the mother's body",["Fetus","Foetus"],[]]},"SYNONYMS":["Abortus"]},"ABORTUSES":{"MEANINGS":{},"SYNONYMS":["Abortus"]},"ABOVE":{"MEANINGS":{"1":["Adverb","at an earlier place",[],["see above"]],"2":["Adverb","in or to a place that is higher",[],[]]},"ANTONYMS":["below"],"SYNONYMS":["Above","Higher up","To a higher place","In a higher place","Supra"]},"ABOVEBOARD":{"MEANINGS":{"1":["Adjective","without concealment or deception; honest",[],["their business was open and aboveboard","straightforward in all his business affairs"]]},"ANTONYMS":["dishonestly"],"SYNONYMS":["Honestly","Aboveboard","Straightforward"]},"ABOVEGROUND":{"MEANINGS":{"1":["Adjective","on or above the surface of the ground",[],["aboveground nuclear testing","surface instruments for detecting oil deposits","surface transportation"]]},"SYNONYMS":["Aboveground"]},"ABOVES":{"MEANINGS":{},"SYNONYMS":["Above"]},"ABRACADABRA":{"MEANINGS":{"1":["Noun","gibberish and nonsense",["Gibberish","Gibber"],[]]},"SYNONYMS":["Abracadabra"]},"ABRACHIA":{"MEANINGS":{"1":["Noun","the condition of having no arms",["Abnormality","Abnormalcy"],[]]},"SYNONYMS":["Abrachia"]},"ABRACHIAS":{"MEANINGS":{},"SYNONYMS":["Abrachia"]},"ABRADANT":{"MEANINGS":{},"SYNONYMS":["Abrader","Abradant","Abrasive","Abrasive material"]},"ABRADANTS":{"MEANINGS":{},"SYNONYMS":["Abrader","Abradant","Abrasive","Abrasive material"]},"ABRADE":{"MEANINGS":{"1":["Verb","wear away",["Wear away","Wear off"],[]]},"SYNONYMS":["Abrase","Corrade","Rub off","Scour","Rub down"]},"ABRADED":{"MEANINGS":{},"SYNONYMS":["Abrase","Corrade","Rub off","Scour","Rub down"]},"ABRADER":{"MEANINGS":{"1":["Noun","a tool or machine used for wearing down or smoothing or polishing",["Tool"],[]]},"SYNONYMS":["Abrader","Abradant"]},"ABRADERS":{"MEANINGS":{},"SYNONYMS":["Abrader","Abradant"]},"ABRADES":{"MEANINGS":{},"SYNONYMS":["Abrase","Corrade","Rub off","Scour","Rub down"]},"ABRADING":{"MEANINGS":{},"SYNONYMS":["Abrase","Corrade","Rub off","Scour","Rub down"]},"ABRAMIS":{"MEANINGS":{"1":["Noun","European fishes",["Fish genus"],[]]},"SYNONYMS":["Abramis","Genus abramis"]},"ABRANCHIAL":{"MEANINGS":{},"ANTONYMS":["branchiate"],"SYNONYMS":["Abranchious","Gill-less","Abranchiate","Abranchial"]},"ABRANCHIATE":{"MEANINGS":{"1":["Adjective","having no gills",[],[]]},"ANTONYMS":["branchiate"],"SYNONYMS":["Abranchious","Gill-less","Abranchiate","Abranchial"]},"ABRANCHIOUS":{"MEANINGS":{},"ANTONYMS":["branchiate"],"SYNONYMS":["Abranchious","Gill-less","Abranchiate","Abranchial"]},"ABRASE":{"MEANINGS":{},"SYNONYMS":["Abrase","Corrade","Rub off","Rub down","Abrade"]},"ABRASED":{"MEANINGS":{},"SYNONYMS":["Abrase","Corrade","Rub off","Rub down","Abrade"]},"ABRASING":{"MEANINGS":{},"SYNONYMS":["Abrase","Corrade","Rub off","Rub down","Abrade"]},"ABRASION":{"MEANINGS":{"1":["Noun","an abraded area where the skin is torn or worn off",["Wound","Lesion"],[]],"2":["Noun","erosion by friction",["Erosion","Eroding","Eating away","Wearing","Wearing away"],[]]},"SYNONYMS":["Excoriation","Scratch","Grinding","Detrition","Abrasion"]},"ABRASIONS":{"MEANINGS":{},"SYNONYMS":["Excoriation","Scratch","Grinding","Detrition","Abrasion"]},"ABRASIVE":{"MEANINGS":{"1":["Adjective","causing abrasion",[],[]]},"SYNONYMS":["Harsh","Abradant","Abrasive material","Abrasive","Scratchy"]},"ABRASIVENESS":{"MEANINGS":{"2":["Noun","the quality of being sharply disagreeable",["Disagreeableness"],[]]},"SYNONYMS":["Abrasiveness","Harshness","Scratchiness"]},"ABRASIVENESSES":{"MEANINGS":{},"SYNONYMS":["Abrasiveness","Harshness","Scratchiness"]},"ABRASIVES":{"MEANINGS":{},"SYNONYMS":["Abradant","Abrasive","Abrasive material"]},"ABREACT":{"MEANINGS":{"1":["Verb","discharge bad feelings or tension through verbalization",["Still","Allay","Relieve","Ease"],[]]},"SYNONYMS":["Abreact"]},"ABREACTED":{"MEANINGS":{},"SYNONYMS":["Abreact"]},"ABREACTING":{"MEANINGS":{},"SYNONYMS":["Abreact"]},"ABREACTION":{"MEANINGS":{},"SYNONYMS":["Catharsis","Abreaction","Katharsis"]},"ABREACTIONS":{"MEANINGS":{},"SYNONYMS":["Catharsis","Abreaction","Katharsis"]},"ABREACTS":{"MEANINGS":{},"SYNONYMS":["Abreact"]},"ABREAST":{"MEANINGS":{"1":["Adverb","alongside each other, facing in the same direction",[],[]]},"SYNONYMS":["Au courant","Up on","Abreast","Au fait"]},"ABRIDGE":{"MEANINGS":{"1":["Verb","reduce in scope while retaining essential elements",["Decrease","Lessen","Minify"],["The manuscript must be shortened"]],"2":["Verb","lessen, diminish, or curtail",["Restrict","Curtail","Curb","Cut back"],["the new law might abridge our freedom of expression"]]},"ANTONYMS":["expand"],"SYNONYMS":["Shorten","Foreshorten","Reduce","Cut","Abbreviate"]},"ABRIDGED":{"MEANINGS":{"1":["Adjective","(used of texts) shortened by condensing or rewriting",[],["an abridged version"]]},"ANTONYMS":["expand","unabridged"],"SYNONYMS":["Shorten","Foreshorten","Reduce","Cut","Abbreviate"]},"ABRIDGEMENT":{"MEANINGS":{},"SYNONYMS":["Capsule","Abridgement","Abridgment","Condensation"]},"ABRIDGEMENTS":{"MEANINGS":{},"SYNONYMS":["Capsule","Abridgement","Abridgment","Condensation"]},"ABRIDGER":{"MEANINGS":{"1":["Noun","one who shortens or abridges or condenses a written work",["Redact","Redactor","Reviser","Rewriter","Rewrite man"],[]]},"SYNONYMS":["Abbreviator","Abridger"]},"ABRIDGERS":{"MEANINGS":{},"SYNONYMS":["Abbreviator","Abridger"]},"ABRIDGES":{"MEANINGS":{},"ANTONYMS":["expand"],"SYNONYMS":["Shorten","Foreshorten","Reduce","Cut","Abbreviate"]},"ABRIDGING":{"MEANINGS":{},"ANTONYMS":["expand"],"SYNONYMS":["Shorten","Foreshorten","Reduce","Cut","Abbreviate"]},"ABRIDGMENT":{"MEANINGS":{},"SYNONYMS":["Capsule","Abridgement","Abridgment","Condensation"]},"ABRIDGMENTS":{"MEANINGS":{},"SYNONYMS":["Capsule","Abridgement","Abridgment","Condensation"]},"ABROACH":{"MEANINGS":{"1":["Adjective","of a cask or barrel",[],["the cask was set abroach"]]},"SYNONYMS":["Broached","Abroach"]},"ABROAD":{"MEANINGS":{"1":["Adverb","to or in a foreign country",[],["they had never travelled abroad"]]},"SYNONYMS":["Overseas","Afield","Abroad"]},"ABROCOMA":{"MEANINGS":{"1":["Noun","abrocomes",["Mammal genus"],[]]},"SYNONYMS":["Abrocoma","Genus abrocoma"]},"ABROCOME":{"MEANINGS":{"1":["Noun","ratlike rodent with soft fur and large ears of the Andes",["Rodent","Gnawer"],[]]},"SYNONYMS":["Chinchilla rat","Abrocome","Rat chinchilla"]},"ABROGATE":{"MEANINGS":{"1":["Verb","revoke formally",["Abolish","Get rid of"],[]]},"SYNONYMS":["Abrogate"]},"ABROGATED":{"MEANINGS":{},"SYNONYMS":["Abrogate"]},"ABROGATES":{"MEANINGS":{},"SYNONYMS":["Abrogate"]},"ABROGATING":{"MEANINGS":{},"SYNONYMS":["Abrogate"]},"ABROGATION":{"MEANINGS":{"1":["Noun","the act of abrogating; an official or legal cancellation",["Cancellation"],[]]},"SYNONYMS":["Abrogation","Annulment","Repeal"]},"ABROGATIONS":{"MEANINGS":{},"SYNONYMS":["Abrogation","Annulment","Repeal"]},"ABROGATOR":{"MEANINGS":{"1":["Noun","an authority or official empowered to abolish or annul or repeal",["Authority"],[]]},"SYNONYMS":["Abrogator"]},"ABROGATORS":{"MEANINGS":{},"SYNONYMS":["Abrogator"]},"ABRONIA":{"MEANINGS":{"1":["Noun","genus of western North American herbs having showy flowers",["Caryophylloid dicot genus"],[]]},"SYNONYMS":["Abronia","Genus abronia"]},"ABRUPT":{"MEANINGS":{"1":["Adjective","marked by sudden changes in subject and sharp transitions",[],["abrupt prose"]],"2":["Adjective","exceedingly sudden and unexpected",[],["came to an abrupt stop","an abrupt change in the weather"]],"3":["Adjective","extremely steep",[],["an abrupt canyon","the precipitous rapids of the upper river","the precipitous hills of Chinese paintings","a sharp drop"]],"4":["Adjective","surprisingly and unceremoniously brusque in manner",[],["an abrupt reply"]]},"SYNONYMS":["Disconnected","Sharp","Precipitous","Abrupt"]},"ABRUPTER":{"MEANINGS":{},"SYNONYMS":["Disconnected","Sharp","Precipitous","Abrupt"]},"ABRUPTEST":{"MEANINGS":{},"SYNONYMS":["Disconnected","Sharp","Precipitous","Abrupt"]},"ABRUPTION":{"MEANINGS":{},"SYNONYMS":["Abruption","Breaking off"]},"ABRUPTLY":{"MEANINGS":{"1":["Adverb","quickly and without warning",[],["he stopped suddenly"]]},"SYNONYMS":["Abruptly","Short","Dead","Suddenly"]},"ABRUPTNESS":{"MEANINGS":{"1":["Noun","an abrupt discourteous manner",["Discourtesy","Rudeness"],[]],"2":["Noun","the property possessed by a slope that is very steep",["Gradient","Slope"],[]],"3":["Noun","the quality of happening with headlong haste or without warning",["Haste","Hastiness","Hurry","Hurriedness","Precipitation"],[]]},"ANTONYMS":["gradualness"],"SYNONYMS":["Curtness","Precipitousness","Precipitateness","Suddenness","Shortness"]},"ABRUZZI":{"MEANINGS":{"1":["Noun","a mountainous region of central Italy on the Adriatic",[],[]]},"SYNONYMS":["Abruzzi","Abruzzi e molise"]},"ABSCESS":{"MEANINGS":{"1":["Noun","symptom consisting of a localized collection of pus surrounded by inflamed tissue",["Symptom"],[]]},"SYNONYMS":["Abscess"]},"ABSCESSED":{"MEANINGS":{"1":["Adjective","infected and filled with pus",[],["an abscessed tooth"]]},"SYNONYMS":["Abscessed"]},"ABSCESSES":{"MEANINGS":{},"SYNONYMS":["Abscess"]},"ABSCISE":{"MEANINGS":{"1":["Verb","shed flowers and leaves and fruit following formation of a scar tissue",["Shed","Cast","Cast off","Shake off","Throw","Throw off","Throw away","Drop"],[]],"2":["Verb","remove or separate by abscission",["Cut off","Chop off","Lop off"],[]]},"SYNONYMS":["Abscise"]},"ABSCISED":{"MEANINGS":{},"SYNONYMS":["Abscise"]},"ABSCISES":{"MEANINGS":{},"SYNONYMS":["Abscise"]},"ABSCISING":{"MEANINGS":{},"SYNONYMS":["Abscise"]},"ABSCISSA":{"MEANINGS":{"1":["Noun","the value of a coordinate on the horizontal axis",["Cartesian coordinate"],[]]},"SYNONYMS":["Abscissa"]},"ABSCISSAE":{"MEANINGS":{},"SYNONYMS":["Abscissa"]},"ABSCISSAS":{"MEANINGS":{},"SYNONYMS":["Abscissa"]},"ABSCISSION":{"MEANINGS":{"1":["Noun","shedding of flowers and leaves and fruit following formation of scar tissue in a plant",["Shedding","Sloughing"],[]],"2":["Noun","the act of cutting something off",["Removal","Remotion"],[]]},"SYNONYMS":["Abscission","Cutting off"]},"ABSCISSIONS":{"MEANINGS":{},"SYNONYMS":["Abscission","Cutting off"]},"ABSCOND":{"MEANINGS":{"1":["Verb","run away; usually includes taking something or somebody along",["Flee","Fly","Take flight"],["The thief made off with our silver","the accountant absconded with the cash from the safe"]]},"SYNONYMS":["Absquatulate","Run off","Decamp","Abscond","Bolt"]},"ABSCONDED":{"MEANINGS":{},"SYNONYMS":["Absquatulate","Run off","Decamp","Abscond","Bolt"]},"ABSCONDER":{"MEANINGS":{"1":["Noun","a fugitive who runs away and hides to avoid arrest or prosecution",["Fugitive","Fugitive from justice"],[]]},"SYNONYMS":["Absconder"]},"ABSCONDERS":{"MEANINGS":{},"SYNONYMS":["Absconder"]},"ABSCONDING":{"MEANINGS":{},"SYNONYMS":["Absquatulate","Run off","Decamp","Abscond","Bolt"]},"ABSCONDS":{"MEANINGS":{},"SYNONYMS":["Absquatulate","Run off","Decamp","Abscond","Bolt"]},"ABSEIL":{"MEANINGS":{},"SYNONYMS":["Rope down","Rappel","Abseil"]},"ABSEILED":{"MEANINGS":{},"SYNONYMS":["Rope down","Rappel","Abseil"]},"ABSEILING":{"MEANINGS":{},"SYNONYMS":["Rope down","Rappel","Abseil"]},"ABSEILS":{"MEANINGS":{},"SYNONYMS":["Rope down","Rappel","Abseil"]},"ABSENCE":{"MEANINGS":{"1":["Noun","the state of being absent",["Lack","Deficiency","Want"],["he was surprised by the absence of any explanation"]],"2":["Noun","failure to be present",["Nonattendance"],[]],"3":["Noun","the time interval during which something or somebody is away",["Time interval","Interval"],["he visited during my absence"]],"4":["Noun","the occurrence of an abrupt, transient loss or impairment of consciousness (which is not subsequently remembered), sometimes with light twitching, fluttering eyelids, etc.; common in petit mal epilepsy",["Seizure","Ictus","Raptus"],[]]},"ANTONYMS":["presence"],"SYNONYMS":["Absence","Absence seizure"]},"ABSENCES":{"MEANINGS":{},"ANTONYMS":["presence"],"SYNONYMS":["Absence","Absence seizure"]},"ABSENT":{"MEANINGS":{"1":["Adjective","not being in a specified place",[],[]],"3":["Adjective","lost in thought; showing preoccupation",[],["an absent stare","an absentminded professor","the scatty glancing quality of a hyperactive but unfocused intelligence"]]},"ANTONYMS":["present"],"SYNONYMS":["Missing","Absent","Lacking","Scatty","Absentminded"]},"ABSENTED":{"MEANINGS":{},"SYNONYMS":["Remove","Absent"]},"ABSENTEE":{"MEANINGS":{"1":["Noun","one that is absent or not in residence",["Traveler","Traveller"],[]]},"SYNONYMS":["Absentee"]},"ABSENTEEISM":{"MEANINGS":{"1":["Noun","habitual absence from work",["Absence"],[]]},"SYNONYMS":["Absenteeism"]},"ABSENTEES":{"MEANINGS":{},"SYNONYMS":["Absentee"]},"ABSENTER":{"MEANINGS":{},"ANTONYMS":["present"],"SYNONYMS":["Missing","Absent","Lacking","Scatty","Absentminded"]},"ABSENTING":{"MEANINGS":{},"SYNONYMS":["Remove","Absent"]},"ABSENTLY":{"MEANINGS":{"1":["Adverb","in an absentminded or preoccupied manner",[],["he read the letter absently"]]},"SYNONYMS":["Abstractedly","Inattentively","Absentmindedly","Absently"]},"ABSENTMINDED":{"MEANINGS":{},"SYNONYMS":["Scatty","Abstracted","Absent","Absentminded"]},"ABSENTMINDEDLY":{"MEANINGS":{},"SYNONYMS":["Abstractedly","Inattentively","Absentmindedly","Absently"]},"ABSENTMINDEDNESS":{"MEANINGS":{"1":["Noun","preoccupation so great that the ordinary demands on attention are ignored",["Preoccupation","Preoccupancy","Absorption","Engrossment"],[]]},"SYNONYMS":["Absentmindedness"]},"ABSENTMINDEDNESSES":{"MEANINGS":{},"SYNONYMS":["Absentmindedness"]},"ABSENTS":{"MEANINGS":{},"SYNONYMS":["Remove","Absent"]},"ABSINTH":{"MEANINGS":{"1":["Noun","strong green liqueur flavored with wormwood and anise",["Liqueur","Cordial"],[]]},"SYNONYMS":["Absinth","Absinthe"]},"ABSINTHE":{"MEANINGS":{},"SYNONYMS":["Old man","Absinthe","Common wormwood","Artemisia absinthium","Absinth"]},"ABSINTHES":{"MEANINGS":{},"SYNONYMS":["Old man","Absinthe","Common wormwood","Artemisia absinthium","Absinth"]},"ABSINTHS":{"MEANINGS":{},"SYNONYMS":["Absinth","Absinthe"]},"ABSOLUTE":{"MEANINGS":{"1":["Adjective","perfect or complete or pure",[],["absolute loyalty","absolute silence","absolute truth","absolute alcohol"]],"2":["Adjective","complete and without restriction or qualification; sometimes used informally as intensifiers",[],["absolute freedom","an absolute dimwit","a downright lie","out-and-out mayhem","an out-and-out lie","a rank outsider","many right-down vices","got the job through sheer persistence","sheer stupidity"]],"3":["Adjective","not limited by law",[],["an absolute monarch"]],"4":["Adjective","expressing finality with no implication of possible change",[],["an absolute guarantee to respect the nation's authority"]],"5":["Adjective","not capable of being violated or infringed",[],["infrangible human rights"]]},"ANTONYMS":["relative"],"SYNONYMS":["Sheer","Infrangible","Out-and-out","Inviolable","Rank"]},"ABSOLUTELY":{"MEANINGS":{"1":["Adverb","completely and without qualification; used informally as intensifiers",[],["an absolutely magnificent painting","a perfectly idiotic idea","you're perfectly right","utterly miserable","you can be dead sure of my innocence","was dead tired","dead right"]],"2":["Adverb","totally and definitely; without question",[],["we are absolutely opposed to the idea","he forced himself to lie absolutely still","iron is absolutely necessary"]]},"SYNONYMS":["Dead","Absolutely","Utterly","Perfectly"]},"ABSOLUTENESS":{"MEANINGS":{"2":["Noun","the quality of being absolute",["Changelessness","Unchangeability","Unchangeableness","Unchangingness"],["the absoluteness of the pope's decree could not be challenged"]]},"SYNONYMS":["Starkness","Utterness","Absoluteness"]},"ABSOLUTER":{"MEANINGS":{},"ANTONYMS":["relative"],"SYNONYMS":["Sheer","Infrangible","Out-and-out","Inviolable","Rank"]},"ABSOLUTES":{"MEANINGS":{},"SYNONYMS":["Absolute"]},"ABSOLUTEST":{"MEANINGS":{},"ANTONYMS":["relative"],"SYNONYMS":["Sheer","Infrangible","Out-and-out","Inviolable","Rank"]},"ABSOLUTION":{"MEANINGS":{"1":["Noun","the condition of being formally forgiven by a priest in the sacrament of penance",["Condition","Status"],[]],"2":["Noun","the act of absolving or remitting; formal redemption as pronounced by a priest in the sacrament of penance",["Redemption","Salvation"],[]]},"SYNONYMS":["Remission of sin","Absolution","Remittal","Remission"]},"ABSOLUTIONS":{"MEANINGS":{},"SYNONYMS":["Remission of sin","Absolution","Remittal","Remission"]},"ABSOLUTISM":{"MEANINGS":{"1":["Noun","dominance through threat of punishment and violence",["Dominance","Ascendance","Ascendence","Ascendancy","Ascendency","Control"],[]],"3":["Noun","the principle of complete and unrestricted power in government",["Political orientation","Ideology","Political theory"],[]],"4":["Noun","the doctrine of an absolute being",["Doctrine","Philosophy","Philosophical system","School of thought","Ism"],[]]},"SYNONYMS":["Despotism","Totalitarianism","Authoritarianism","One-man rule","Shogunate"]},"ABSOLUTIST":{"MEANINGS":{"1":["Adjective","pertaining to the principle of totalitarianism",[],[]]},"SYNONYMS":["Absolutist","Absolutistic"]},"ABSOLUTISTIC":{"MEANINGS":{},"SYNONYMS":["Absolutist","Absolutistic"]},"ABSOLUTISTS":{"MEANINGS":{},"SYNONYMS":["Absolutist"]},"ABSOLVE":{"MEANINGS":{"2":["Verb","let off the hook",["Forgive"],["I absolve you from this responsibility"]]},"ANTONYMS":["blame"],"SYNONYMS":["Free","Absolve","Justify","Shrive"]},"ABSOLVED":{"MEANINGS":{"1":["Adjective","freed from any question of guilt",[],["is absolved from all blame","was now clear of the charge of cowardice","his official honor is vindicated"]]},"ANTONYMS":["blame"],"SYNONYMS":["Absolve","Justify","Exonerated","Free","Clear"]},"ABSOLVER":{"MEANINGS":{"1":["Noun","someone who grants absolution",["Pardoner"],[]]},"SYNONYMS":["Absolver"]},"ABSOLVERS":{"MEANINGS":{},"SYNONYMS":["Absolver"]},"ABSOLVES":{"MEANINGS":{},"ANTONYMS":["blame"],"SYNONYMS":["Free","Absolve","Justify","Shrive"]},"ABSOLVING":{"MEANINGS":{},"ANTONYMS":["blame"],"SYNONYMS":["Free","Absolve","Justify","Shrive"]},"ABSOLVITORY":{"MEANINGS":{"1":["Adjective","providing absolution",[],[]]},"SYNONYMS":["Forgiving","Exonerative","Absolvitory"]},"ABSORB":{"MEANINGS":{"1":["Verb","become imbued",["Sorb","Take up"],["The liquids, light, and gases absorb"]],"2":["Verb","take up mentally",["Learn","Larn","Acquire"],["he absorbed the knowledge or beliefs of his tribe"]],"3":["Verb","take up, as of debts or payments",["Fund"],["absorb the costs for something"]],"4":["Verb","take in, also metaphorically",[],["The sponge absorbs water well","She drew strength from the minister's words"]],"5":["Verb","cause to become one with",["Blend","Flux","Mix","Conflate","Commingle","Immix","Fuse","Coalesce","Meld","Combine","Merge"],["The sales tax is absorbed into the state income tax"]],"6":["Verb","suck or take up or in",[],["A black star absorbs all matter"]],"8":["Verb","assimilate or take in",["Receive","Take in","Invite"],["The immigrants were quickly absorbed into society"]],"9":["Verb","consume all of one's attention or time",["Interest"],["Her interest in butterflies absorbs her completely"]]},"ANTONYMS":["emit"],"SYNONYMS":["Engage","Imbibe","Steep","Occupy","Suck"]},"ABSORBABLE":{"MEANINGS":{"1":["Adjective","capable of being absorbed or taken in through the pores of a surface",[],[]]},"ANTONYMS":["adsorbable"],"SYNONYMS":["Absorbable"]},"ABSORBANCE":{"MEANINGS":{},"SYNONYMS":["Absorbance","Optical density","Transmission density","Photographic density"]},"ABSORBED":{"MEANINGS":{"2":["Adjective","retained without reflection",[],["the absorbed light intensity"]]},"ANTONYMS":["emit"],"SYNONYMS":["Engage","Engrossed","Imbibe","Wrapped","Steep"]},"ABSORBEFACIENT":{"MEANINGS":{"1":["Adjective","inducing or promoting absorption",[],[]]},"SYNONYMS":["Sorbefacient","Absorbefacient"]},"ABSORBENCY":{"MEANINGS":{"1":["Noun","the property of being absorbent",["Permeability","Permeableness"],[]]},"ANTONYMS":["nonabsorbency"],"SYNONYMS":["Absorbency"]},"ABSORBENCIES":{"MEANINGS":{},"ANTONYMS":["nonabsorbency"],"SYNONYMS":["Absorbency"]},"ABSORBENT":{"MEANINGS":{"1":["Adjective","having power or capacity or tendency to absorb or soak up something (liquids or energy etc.)",[],["as absorbent as a sponge"]]},"ANTONYMS":["nonabsorbent"],"SYNONYMS":["Absorptive","Absorbent","Absorbent material"]},"ABSORBENTS":{"MEANINGS":{},"SYNONYMS":["Absorbent","Absorbent material"]},"ABSORBER":{"MEANINGS":{"1":["Noun","(physics) material in a nuclear reactor that absorbs radiation",["Absorbent material","Absorbent"],[]]},"SYNONYMS":["Absorber"]},"ABSORBERS":{"MEANINGS":{},"SYNONYMS":["Absorber"]},"ABSORBING":{"MEANINGS":{"1":["Adjective","capable of arousing and holding the attention",[],["a fascinating story"]]},"ANTONYMS":["emit"],"SYNONYMS":["Engage","Riveting","Gripping","Absorbing","Imbibe"]},"ABSORBS":{"MEANINGS":{},"ANTONYMS":["emit"],"SYNONYMS":["Engage","Imbibe","Steep","Occupy","Suck"]},"ABSORPTANCE":{"MEANINGS":{},"SYNONYMS":["Absorptance","Absorption coefficient","Coefficient of absorption"]},"ABSORPTION":{"MEANINGS":{"1":["Noun","(chemistry) a process in which one substance permeates another; a fluid permeates or is dissolved by a liquid or solid",["Sorption"],[]],"2":["Noun","(physics) the process in which incident radiated energy is retained without reflection or transmission on passing through a medium",["Natural process","Natural action","Action","Activity"],["the absorption of photons by atoms or molecules"]]},"SYNONYMS":["Absorption","Concentration","Soaking up","Immersion","Preoccupancy"]},"ABSORPTIONS":{"MEANINGS":{},"SYNONYMS":["Absorption","Concentration","Soaking up","Immersion","Preoccupancy"]},"ABSORPTIVE":{"MEANINGS":{},"ANTONYMS":["nonabsorbent"],"SYNONYMS":["Absorptive","Absorbent"]},"ABSORPTIVITY":{"MEANINGS":{"1":["Noun","(physics) the property of a body that determines the fraction of the incident radiation or sound flux absorbed or absorbable by the body",["Physical property"],[]]},"SYNONYMS":["Absorptivity","Absorption factor"]},"ABSQUATULATE":{"MEANINGS":{},"SYNONYMS":["Absquatulate","Run off","Decamp","Abscond","Bolt"]},"ABSTAIN":{"MEANINGS":{"1":["Verb","refrain from voting",["Refrain","Forbear"],[]],"2":["Verb","choose not to consume",[],["I abstain from alcohol"]]},"ANTONYMS":["consume"],"SYNONYMS":["Refrain","Desist","Abstain"]},"ABSTAINED":{"MEANINGS":{},"ANTONYMS":["consume"],"SYNONYMS":["Refrain","Desist","Abstain"]},"ABSTAINER":{"MEANINGS":{"1":["Noun","someone who practices self denial as a spiritual discipline",["Religious person"],[]],"2":["Noun","a person who refrains from drinking intoxicating beverages",["Person","Individual","Someone","Somebody","Mortal","Soul"],[]]},"ANTONYMS":["drinker"],"SYNONYMS":["Nondrinker","Abstainer","Ascetic","Abstinent"]},"ABSTAINERS":{"MEANINGS":{},"ANTONYMS":["drinker"],"SYNONYMS":["Nondrinker","Abstainer","Ascetic","Abstinent"]},"ABSTAINING":{"MEANINGS":{},"ANTONYMS":["consume"],"SYNONYMS":["Refrain","Desist","Abstain"]},"ABSTAINS":{"MEANINGS":{},"ANTONYMS":["consume"],"SYNONYMS":["Refrain","Desist","Abstain"]},"ABSTEMIOUS":{"MEANINGS":{"1":["Adjective","sparing in consumption of especially food and drink",[],["the pleasures of the table, never of much consequence to one naturally abstemious\"- John Galsworthy"]],"2":["Adjective","marked by temperance in indulgence",[],["abstemious with the use of adverbs","a light eater","a light smoker","ate a light supper"]]},"ANTONYMS":["gluttonous"],"SYNONYMS":["Abstemious","Light"]},"ABSTEMIOUSLY":{"MEANINGS":{"1":["Adverb","in a sparing manner; without overindulgence",[],["he ate and drank abstemiously","indulged temperately in cocktails"]]},"SYNONYMS":["Temperately","Abstemiously"]},"ABSTEMIOUSNESS":{"MEANINGS":{"1":["Noun","restricted to bare necessities",["Meagerness","Meagreness","Leanness","Poorness","Scantiness","Scantness","Exiguity"],[]],"2":["Noun","moderation in eating and drinking",["Temperance","Moderation"],[]]},"SYNONYMS":["Abstemiousness"]},"ABSTENTION":{"MEANINGS":{},"SYNONYMS":["Abstinence","Abstention"]},"ABSTENTIONS":{"MEANINGS":{},"SYNONYMS":["Abstinence","Abstention"]},"ABSTENTIOUS":{"MEANINGS":{},"SYNONYMS":["Abstentious","Abstinent"]},"ABSTINENCE":{"MEANINGS":{"1":["Noun","the trait of abstaining (especially from alcohol)",["Self-discipline","Self-denial"],[]],"2":["Noun","act or practice of refraining from indulging an appetite",["Self-denial","Self-discipline","Self-control"],[]]},"SYNONYMS":["Abstinence","Abstention"]},"ABSTINENCES":{"MEANINGS":{},"SYNONYMS":["Abstinence","Abstention"]},"ABSTINENT":{"MEANINGS":{"1":["Adjective","self-restraining; not indulging an appetite especially for food or drink",[],["not totally abstinent but abstemious"]]},"ANTONYMS":["drinker"],"SYNONYMS":["Abstentious","Nondrinker","Abstainer","Abstinent"]},"ABSTRACT":{"MEANINGS":{"1":["Adjective","existing only in the mind; separated from embodiment",[],["abstract words like `truth' and `justice'"]],"2":["Adjective","not representing or imitating external reality or the objects of nature",[],["a large abstract painting"]],"3":["Adjective","dealing with a subject in the abstract without practical purpose or intention",[],["abstract reasoning","abstract science"]],"4":["Verb","give an abstract (of)",["Sum up","Summarize","Summarise","Resume"],[]]},"ANTONYMS":["concrete"],"SYNONYMS":["Pilfer","Synopsis","Snarf","Nonobjective","Pinch"]},"ABSTRACTED":{"MEANINGS":{},"SYNONYMS":["Pilfer","Absent","Scatty","Snarf","Abstract"]},"ABSTRACTEDLY":{"MEANINGS":{},"SYNONYMS":["Abstractedly","Inattentively","Absentmindedly","Absently"]},"ABSTRACTEDNESS":{"MEANINGS":{"1":["Noun","preoccupation with something to the exclusion of all else",["Preoccupation","Preoccupancy","Absorption","Engrossment"],[]]},"SYNONYMS":["Abstractedness","Abstraction"]},"ABSTRACTER":{"MEANINGS":{},"ANTONYMS":["concrete"],"SYNONYMS":["Abstracter","Abstract","Nonobjective","Abstractor","Nonfigurative"]},"ABSTRACTERS":{"MEANINGS":{},"SYNONYMS":["Abstracter","Abstractor"]},"ABSTRACTEST":{"MEANINGS":{},"ANTONYMS":["concrete"],"SYNONYMS":["Abstractionist","Nonfigurative","Abstract","Nonobjective"]},"ABSTRACTING":{"MEANINGS":{},"SYNONYMS":["Pilfer","Snarf","Abstract","Swipe","Nobble"]},"ABSTRACTION":{"MEANINGS":{"1":["Noun","a concept or idea not associated with any specific instance",["Concept","Conception","Construct"],["he loved her only in the abstract--not in person"]],"2":["Noun","the act of withdrawing or removing something",["Removal","Remotion"],[]],"3":["Noun","the process of formulating general concepts by abstracting common properties of instances",["Theorization","Theorisation"],[]],"4":["Noun","an abstract painting",["Painting","Picture"],[]],"6":["Noun","a general concept formed by extracting common features from specific examples",["Entity"],[]]},"SYNONYMS":["Abstractedness","Abstract","Generalisation","Abstract entity","Generalization"]},"ABSTRACTIONISM":{"MEANINGS":{"1":["Noun","an abstract genre of art; artistic content depends on internal form rather than pictorial representation",["Genre"],[]],"2":["Noun","a representation having no reference to concrete objects or specific examples",["Representation","Mental representation","Internal representation"],[]]},"SYNONYMS":["Abstract art","Unrealism","Abstractionism"]},"ABSTRACTIONIST":{"MEANINGS":{"1":["Noun","a painter of abstract pictures",["Painter"],[]]},"SYNONYMS":["Abstract","Abstract artist","Nonobjective","Nonfigurative","Abstractionist"]},"ABSTRACTIONISTS":{"MEANINGS":{},"SYNONYMS":["Abstractionist","Abstract artist"]},"ABSTRACTIONS":{"MEANINGS":{},"SYNONYMS":["Abstractedness","Abstract","Generalisation","Abstract entity","Generalization"]},"ABSTRACTIVE":{"MEANINGS":{"1":["Adjective","of an abstracting nature or having the power of abstracting",[],["abstractive analysis"]]},"SYNONYMS":["Abstractive"]},"ABSTRACTLY":{"MEANINGS":{"1":["Adverb","in abstract terms",[],[]]},"ANTONYMS":["concretely"],"SYNONYMS":["Abstractly"]},"ABSTRACTNESS":{"MEANINGS":{"1":["Noun","the quality of being considered apart from a specific instance or object",["Immateriality","Incorporeality"],[]]},"ANTONYMS":["concreteness"],"SYNONYMS":["Abstractness"]},"ABSTRACTNESSES":{"MEANINGS":{},"ANTONYMS":["concreteness"],"SYNONYMS":["Abstractness"]},"ABSTRACTOR":{"MEANINGS":{"1":["Noun","one who makes abstracts or summarizes information",["Writer","Author"],[]]},"SYNONYMS":["Abstracter","Abstractor"]},"ABSTRACTORS":{"MEANINGS":{},"SYNONYMS":["Abstracter","Abstractor"]},"ABSTRACTS":{"MEANINGS":{},"SYNONYMS":["Pilfer","Abstraction","Snarf","Abstract","Swipe"]},"ABSTRUSE":{"MEANINGS":{"1":["Adjective","difficult to penetrate; incomprehensible to one of ordinary understanding or knowledge",[],["the professor's lectures were so abstruse that students tended to avoid them","a deep metaphysical theory","some recondite problem in historiography"]]},"SYNONYMS":["Recondite","Deep","Abstruse"]},"ABSTRUSELY":{"MEANINGS":{"1":["Adverb","in a manner difficult to understand",[],["the professor's abstrusely reasoned theories were wasted on his students"]]},"SYNONYMS":["Abstrusely"]},"ABSTRUSENESS":{"MEANINGS":{},"ANTONYMS":["clarity"],"SYNONYMS":["Abstrusity","Reconditeness","Profundity","Profoundness","Obscurity"]},"ABSTRUSENESSES":{"MEANINGS":{},"ANTONYMS":["clarity"],"SYNONYMS":["Abstrusity","Reconditeness","Profundity","Profoundness","Obscurity"]},"ABSTRUSER":{"MEANINGS":{},"SYNONYMS":["Recondite","Deep","Abstruse"]},"ABSTRUSEST":{"MEANINGS":{},"SYNONYMS":["Recondite","Deep","Abstruse"]},"ABSTRUSITY":{"MEANINGS":{},"SYNONYMS":["Abstrusity","Reconditeness","Profundity","Profoundness","Abstruseness"]},"ABSTRUSITIES":{"MEANINGS":{},"SYNONYMS":["Abstrusity","Reconditeness","Profundity","Profoundness","Abstruseness"]},"ABSURD":{"MEANINGS":{"1":["Adjective","inconsistent with reason or logic or common sense",[],["the absurd predicament of seeming to argue that virtue is highly desirable but intensely unpleasant\"- Walter Lippman"]],"2":["Adjective","incongruous; inviting ridicule",[],["the absurd excuse that the dog ate his homework","that's a cockeyed idea","ask a nonsensical question and get a nonsensical answer","a contribution so small as to be laughable","it is ludicrous to call a cottage a mansion","a preposterous attempt to turn back the pages of history","her conceited assumption of universal interest in her rather dull children was ridiculous"]]},"SYNONYMS":["Idiotic","Preposterous","Absurd","Laughable","Ludicrous"]},"ABSURDER":{"MEANINGS":{},"SYNONYMS":["Idiotic","Preposterous","Absurd","Laughable","Ludicrous"]},"ABSURDEST":{"MEANINGS":{},"SYNONYMS":["Idiotic","Preposterous","Absurd","Laughable","Ludicrous"]},"ABSURDITY":{"MEANINGS":{"1":["Noun","a message whose content is at variance with reason",["Nonsense","Bunk","Nonsensicality","Meaninglessness","Hokum"],[]],"2":["Noun","a ludicrous folly",["Folly","Foolishness","Unwiseness"],["the crowd laughed at the absurdity of the clown's behavior"]]},"SYNONYMS":["Absurdness","Absurdity","Fatuity","Silliness","Ridiculousness"]},"ABSURDITIES":{"MEANINGS":{},"SYNONYMS":["Absurdness","Absurdity","Fatuity","Silliness","Ridiculousness"]},"ABSURDLY":{"MEANINGS":{"1":["Adverb","in an absurd manner or to an absurd degree",[],["an absurdly rich young woman"]]},"SYNONYMS":["Absurdly"]},"ABSURDNESS":{"MEANINGS":{},"SYNONYMS":["Absurdity","Absurdness","Ridiculousness"]},"ABSURDS":{"MEANINGS":{},"SYNONYMS":["The absurd","Absurd"]},"ABUKIR":{"MEANINGS":{"1":["Noun","a bay on the Mediterranean Sea in northern Egypt",[],[]]},"SYNONYMS":["Abukir bay","Abukir"]},"ABULIA":{"MEANINGS":{"1":["Noun","a loss of will power",["Psychological state","Psychological condition","Mental state","Mental condition"],[]]},"SYNONYMS":["Abulia","Aboulia"]},"ABULIAS":{"MEANINGS":{},"SYNONYMS":["Abulia","Aboulia"]},"ABULIC":{"MEANINGS":{"1":["Adjective","suffering from abulia; showing abnormal inability to act or make decisions",[],[]]},"SYNONYMS":["Abulic","Aboulic"]},"ABUNDANCE":{"MEANINGS":{"1":["Noun","the property of a more than adequate quantity or supply",["Quantity"],["an age of abundance"]],"2":["Noun","(physics) the ratio of the number of atoms of a specific isotope of an element to the total number of isotopes present",["Ratio"],[]],"3":["Noun","(chemistry) the ratio of the total mass of an element in the earth's crust to the total mass of the earth's crust; expressed as a percentage or in parts per million",["Ratio"],[]]},"ANTONYMS":["scarcity"],"SYNONYMS":["Copiousness","Abundance","Teemingness"]},"ABUNDANCES":{"MEANINGS":{},"ANTONYMS":["scarcity"],"SYNONYMS":["Copiousness","Abundance","Teemingness"]},"ABUNDANT":{"MEANINGS":{"1":["Adjective","present in great quantity",[],["an abundant supply of water"]]},"ANTONYMS":["scarce"],"SYNONYMS":["Abundant"]},"ABUNDANTLY":{"MEANINGS":{"1":["Adverb","in an abundant manner",[],["they were abundantly supplied with food","he thanked her profusely"]]},"SYNONYMS":["Profusely","Extravagantly","Abundantly","Copiously"]},"ABUSE":{"MEANINGS":{"2":["Noun","a rude expression intended to offend or hurt",["Disrespect","Discourtesy"],["when a student made a stupid mistake he spared them no abuse","they yelled insults at the visiting team"]],"3":["Verb","use foul or abusive language towards",["Attack","Round","Assail","Lash out","Snipe","Assault"],["The actress abused the policeman who gave her a parking ticket","The angry mother shouted at the teacher"]],"4":["Verb","use wrongly or improperly or excessively",["Use","Expend"],["Her husband often abuses alcohol","while she was pregnant, she abused drugs"]]},"SYNONYMS":["Shout","Ill-usage","Mistreat","Insult","Contumely"]},"ABUSED":{"MEANINGS":{"1":["Adjective","used improperly or excessively especially drugs",[],["an abused substance"]],"2":["Adjective","subjected to cruel treatment",[],["an abused wife"]]},"ANTONYMS":["unabused"],"SYNONYMS":["Shout","Mistreat","Abused","Blackguard","Mistreated"]},"ABUSER":{"MEANINGS":{"1":["Noun","someone who abuses",["Wrongdoer","Offender"],[]]},"SYNONYMS":["Abuser","Maltreater"]},"ABUSERS":{"MEANINGS":{},"SYNONYMS":["Abuser","Maltreater"]},"ABUSES":{"MEANINGS":{},"SYNONYMS":["Shout","Ill-usage","Mistreat","Insult","Contumely"]},"ABUSING":{"MEANINGS":{},"SYNONYMS":["Shout","Mistreat","Blackguard","Abuse","Step"]},"ABUSIVE":{"MEANINGS":{"1":["Adjective","expressing offensive reproach",[],[]],"2":["Adjective","characterized by physical or psychological maltreatment",[],["abusive punishment","argued...that foster homes are abusive"]]},"SYNONYMS":["Abusive","Opprobrious","Scurrilous"]},"ABUSIVELY":{"MEANINGS":{"1":["Adverb","in an abusive manner",[],["he behaved abusively toward his children"]]},"SYNONYMS":["Abusively"]},"ABUT":{"MEANINGS":{},"SYNONYMS":["Butt","Adjoin","Butt on","Abut","March"]},"ABUTILON":{"MEANINGS":{"1":["Noun","herbs or shrubs or small trees: flowering maple; Indian mallow",["Dilleniid dicot genus"],[]]},"SYNONYMS":["Abutilon","Genus abutilon"]},"ABUTILONS":{"MEANINGS":{},"SYNONYMS":["Abutilon","Genus abutilon"]},"ABUTMENT":{"MEANINGS":{"1":["Noun","point of contact between two objects or parts",["Point"],[]],"2":["Noun","a masonry support that touches and directly receives thrust or pressure of an arch or bridge",["Support"],[]]},"SYNONYMS":["Abutment"]},"ABUTMENTS":{"MEANINGS":{},"SYNONYMS":["Abutment"]},"ABUTS":{"MEANINGS":{},"SYNONYMS":["Butt","Adjoin","Butt on","Abut","March"]},"ABUTTED":{"MEANINGS":{},"SYNONYMS":["Butt","Adjoin","Butt on","Abut","March"]},"ABUTTER":{"MEANINGS":{"1":["Noun","the owner of contiguous property",["Landowner","Landholder","Property owner"],[]]},"SYNONYMS":["Abutter"]},"ABUTTERS":{"MEANINGS":{},"SYNONYMS":["Abutter"]},"ABUTTING":{"MEANINGS":{},"SYNONYMS":["Butt","Adjoin","Butt on","Abut","March"]},"ABUZZ":{"MEANINGS":{"1":["Adjective","noisy like the sound of a bee",[],["the room was abuzz over the latest scandal"]]},"SYNONYMS":["Abuzz","Buzzing"]},"ABVOLT":{"MEANINGS":{"1":["Noun","a unit of potential equal to one-hundred-millionth of a volt",["Potential unit"],[]]},"SYNONYMS":["Abvolt"]},"ABVOLTS":{"MEANINGS":{},"SYNONYMS":["Abvolt"]},"ABWATT":{"MEANINGS":{"1":["Noun","a power unit equal to the power dissipated when 1 abampere flows across a potential difference of 1 abvolt (one ten-thousandth of a milliwatt)",["Power unit"],[]]},"SYNONYMS":["Abwatt"]},"ABWATTS":{"MEANINGS":{},"SYNONYMS":["Abwatt"]},"ACACIA":{"MEANINGS":{"1":["Noun","any of various spiny trees or shrubs of the genus Acacia",["Tree"],[]]},"SYNONYMS":["Acacia"]},"ACACIAS":{"MEANINGS":{},"SYNONYMS":["Acacia"]},"ACADEME":{"MEANINGS":{},"SYNONYMS":["Academia","Academe"]},"ACADEMES":{"MEANINGS":{},"SYNONYMS":["Academia","Academe"]},"ACADEMY":{"MEANINGS":{"1":["Noun","a secondary school (usually private)",["Secondary school","Lyceum","Lycee","Gymnasium","Middle school"],[]],"2":["Noun","an institution for the advancement of art or science or literature",["Institution","Establishment"],[]],"3":["Noun","a school for special training",["School"],[]],"4":["Noun","a learned establishment for the advancement of knowledge",["Establishment"],[]]},"SYNONYMS":["Honorary society","Academy"]},"ACADEMIA":{"MEANINGS":{"1":["Noun","the academic world",["World","Domain"],[]]},"SYNONYMS":["Academia","Academe"]},"ACADEMIAS":{"MEANINGS":{},"SYNONYMS":["Academia","Academe"]},"ACADEMIC":{"MEANINGS":{"1":["Adjective","associated with academia or an academy",[],["the academic curriculum","academic gowns"]],"2":["Adjective","hypothetical or theoretical and not expected to produce an immediate or practical result",[],["an academic discussion","an academic question"]],"3":["Adjective","marked by a narrow focus on or display of learning especially its trivial aspects",[],[]]},"SYNONYMS":["Donnish","Pedantic","Academician","Faculty member","Academic"]},"ACADEMICALLY":{"MEANINGS":{"1":["Adverb","in regard to academic matters",[],["academically, this is a good school"]]},"SYNONYMS":["Academically"]},"ACADEMICIAN":{"MEANINGS":{"1":["Noun","someone elected to honorary membership in an academy",["Honoree"],[]],"2":["Noun","a scholar who is skilled in academic disputation",["Scholar","Scholarly person","Bookman","Student"],[]],"3":["Noun","an educator who works at a college or university",["Educator","Pedagogue","Pedagog"],[]]},"SYNONYMS":["Schoolman","Academician","Academic","Faculty member"]},"ACADEMICIANS":{"MEANINGS":{},"SYNONYMS":["Schoolman","Academician","Academic","Faculty member"]},"ACADEMICIANSHIP":{"MEANINGS":{"1":["Noun","the position of member of an honorary academy",["Position","Post","Berth","Office","Spot","Billet","Place","Situation"],[]]},"SYNONYMS":["Academicianship"]},"ACADEMICISM":{"MEANINGS":{},"SYNONYMS":["Academism","Academicism","Scholasticism"]},"ACADEMICS":{"MEANINGS":{},"SYNONYMS":["Academician","Academic","Faculty member"]},"ACADEMIES":{"MEANINGS":{},"SYNONYMS":["Honorary society","Academy"]},"ACADEMISM":{"MEANINGS":{},"SYNONYMS":["Academism","Academicism","Scholasticism"]},"ACALYPHA":{"MEANINGS":{"1":["Noun","a genus of herbs and shrubs belonging to the family Euphorbiaceae",["Rosid dicot genus"],[]]},"SYNONYMS":["Acalypha","Genus acalypha"]},"ACANTHA":{"MEANINGS":{},"SYNONYMS":["Acantha","Spine","Spur"]},"ACANTHACEAE":{"MEANINGS":{"1":["Noun","widely distributed herbs and shrubs and trees; sometimes placed in the order Scrophulariales",["Asterid dicot family"],[]]},"SYNONYMS":["Family acanthaceae","Acanthus family","Acanthaceae"]},"ACANTHI":{"MEANINGS":{},"SYNONYMS":["Acanthus"]},"ACANTHION":{"MEANINGS":{"1":["Noun","the craniometric point at the anterior extremity of the intermaxillary suture",["Craniometric point"],[]]},"SYNONYMS":["Acanthion"]},"ACANTHOCEPHALA":{"MEANINGS":{"1":["Noun","phylum or class of elongated wormlike parasites that live in the intestines of vertebrates: spiny-headed worms",["Phylum"],[]]},"SYNONYMS":["Acanthocephala","Phylum acanthocephala"]},"ACANTHOCEPHALAN":{"MEANINGS":{"1":["Noun","any of various worms living parasitically in intestines of vertebrates having a retractile proboscis covered with many hooked spines",["Worm"],[]]},"SYNONYMS":["Spiny-headed worm","Acanthocephalan"]},"ACANTHOCEREUS":{"MEANINGS":{"1":["Noun","mostly trailing cacti having nocturnal white flowers; tropical America and Caribbean region",["Caryophylloid dicot genus"],[]]},"SYNONYMS":["Acanthocereus","Genus acanthocereus"]},"ACANTHOID":{"MEANINGS":{"1":["Adjective","shaped like a spine or thorn",[],[]]},"SYNONYMS":["Spinous","Acanthoid","Acanthous"]},"ACANTHOLYSIS":{"MEANINGS":{"1":["Noun","a breakdown of a cell layer in the epidermis (as in pemphigus)",["Skin disease","Disease of the skin","Skin disorder"],[]]},"SYNONYMS":["Acantholysis"]},"ACANTHOMA":{"MEANINGS":{"1":["Noun","a neoplasm originating in the epidermis",["Tumor","Tumour","Neoplasm"],[]]},"SYNONYMS":["Skin tumor","Acanthoma"]},"ACANTHOMAS":{"MEANINGS":{},"SYNONYMS":["Skin tumor","Acanthoma"]},"ACANTHOPHIS":{"MEANINGS":{"1":["Noun","Australian elapid snakes",["Reptile genus"],[]]},"SYNONYMS":["Genus acanthophis","Acanthophis"]},"ACANTHOPTERYGIAN":{"MEANINGS":{},"ANTONYMS":["soft-finned_fish"],"SYNONYMS":["Spiny-finned fish","Acanthopterygian"]},"ACANTHOPTERYGII":{"MEANINGS":{"1":["Noun","teleost fishes having fins with sharp bony rays",["Animal order"],[]]},"SYNONYMS":["Acanthopterygii","Superorder acanthopterygii"]},"ACANTHOSIS":{"MEANINGS":{"1":["Noun","an abnormal but benign thickening of the prickle-cell layer of the skin (as in psoriasis)",["Skin disease","Disease of the skin","Skin disorder"],[]]},"SYNONYMS":["Acanthosis"]},"ACANTHOTIC":{"MEANINGS":{"1":["Adjective","of or relating to or having acanthosis",[],[]]},"SYNONYMS":["Acanthotic"]},"ACANTHOUS":{"MEANINGS":{},"SYNONYMS":["Spinous","Acanthoid","Acanthous"]},"ACANTHURIDAE":{"MEANINGS":{"1":["Noun","surgeonfishes",["Fish family"],[]]},"SYNONYMS":["Family acanthuridae","Acanthuridae"]},"ACANTHURUS":{"MEANINGS":{"1":["Noun","type genus of the Acanthuridae: doctorfishes",["Fish genus"],[]]},"SYNONYMS":["Genus acanthurus","Acanthurus"]},"ACANTHUS":{"MEANINGS":{"1":["Noun","any plant of the genus Acanthus having large spiny leaves and spikes or white or purplish flowers; native to Mediterranean region but widely cultivated",["Herb","Herbaceous plant"],[]]},"SYNONYMS":["Acanthus"]},"ACANTHUSES":{"MEANINGS":{},"SYNONYMS":["Acanthus"]},"ACAPNIA":{"MEANINGS":{},"ANTONYMS":["hypercapnia"],"SYNONYMS":["Acapnia","Hypocapnia"]},"ACAPNIAL":{"MEANINGS":{},"SYNONYMS":["Acapnic","Acapnotic","Acapnial"]},"ACAPNIAS":{"MEANINGS":{},"ANTONYMS":["hypercapnia"],"SYNONYMS":["Acapnia","Hypocapnia"]},"ACARDIA":{"MEANINGS":{"1":["Noun","congenital absence of the heart (as in the development of some monsters)",["Abnormality","Abnormalcy"],[]]},"SYNONYMS":["Acardia"]},"ACARI":{"MEANINGS":{},"SYNONYMS":["Acarus","Genus acarus"]},"ACARIASIS":{"MEANINGS":{"1":["Noun","infestation with itch mites",["Infestation"],[]]},"SYNONYMS":["Acaridiasis","Acariosis","Acariasis"]},"ACARICIDE":{"MEANINGS":{"1":["Noun","a chemical agent used to kill mites",["Pesticide"],[]]},"SYNONYMS":["Acaricide","Acaracide"]},"ACARID":{"MEANINGS":{"1":["Noun","very small free-living arachnid that is parasitic on animals or plants; related to ticks",["Mite"],[]]},"SYNONYMS":["Acarid"]},"ACARIDAE":{"MEANINGS":{"1":["Noun","mites",["Arthropod family"],[]]},"SYNONYMS":["Family acaridae","Acaridae"]},"ACARIDS":{"MEANINGS":{},"SYNONYMS":["Acarid"]},"ACARINA":{"MEANINGS":{"1":["Noun","mites and ticks",["Animal order"],[]]},"SYNONYMS":["Acarina","Order acarina"]},"ACARINE":{"MEANINGS":{"1":["Noun","mite or tick",["Arachnid","Arachnoid"],[]]},"SYNONYMS":["Acarine"]},"ACARINES":{"MEANINGS":{},"SYNONYMS":["Acarine"]},"ACAROPHOBIA":{"MEANINGS":{"1":["Noun","a morbid fear of small insects and mites and worms",["Zoophobia"],[]]},"SYNONYMS":["Acarophobia"]},"ACARPELLOUS":{"MEANINGS":{},"ANTONYMS":["carpellate"],"SYNONYMS":["Acarpellous","Acarpelous"]},"ACARPELOUS":{"MEANINGS":{"1":["Adjective","having no carpels",[],[]]},"ANTONYMS":["carpellate"],"SYNONYMS":["Acarpellous","Acarpelous"]},"ACARPOUS":{"MEANINGS":{"1":["Adjective","producing no fruit",[],[]]},"SYNONYMS":["Acarpous"]},"ACARUS":{"MEANINGS":{"1":["Noun","any of several mites of the order Acarina",["Mite"],[]]},"SYNONYMS":["Acarus","Genus acarus"]},"ACATALECTIC":{"MEANINGS":{"1":["Adjective","(verse) metrically complete; especially having the full number of syllables in the final metrical foot",[],[]]},"ANTONYMS":["catalectic"],"SYNONYMS":["Acatalectic"]},"ACATAPHASIA":{"MEANINGS":{"1":["Noun","a disorder in which a lesion to the central nervous system leaves you unable to formulate a statement or to express yourself in an organized manner",["Brain disorder","Encephalopathy","Brain disease"],[]]},"SYNONYMS":["Acataphasia"]},"ACAUDAL":{"MEANINGS":{},"ANTONYMS":["caudate"],"SYNONYMS":["Acaudal","Acaudate"]},"ACAUDATE":{"MEANINGS":{"1":["Adjective","lacking a tail or taillike appendage",[],[]]},"ANTONYMS":["caudate"],"SYNONYMS":["Acaudal","Acaudate"]},"ACAULESCENT":{"MEANINGS":{"1":["Adjective","(of plants) having no apparent stem above ground",[],[]]},"ANTONYMS":["caulescent"],"SYNONYMS":["Stemless","Acaulescent"]},"ACCEDE":{"MEANINGS":{"2":["Verb","take on duties or office",["Succeed","Come after","Follow","Take office"],["accede to the throne"]]},"ANTONYMS":["dissent"],"SYNONYMS":["Assent","Enter","Acquiesce","Give in","Accede"]},"ACCEDED":{"MEANINGS":{},"ANTONYMS":["dissent"],"SYNONYMS":["Assent","Enter","Acquiesce","Give in","Accede"]},"ACCEDES":{"MEANINGS":{},"ANTONYMS":["dissent"],"SYNONYMS":["Assent","Enter","Acquiesce","Give in","Accede"]},"ACCEDING":{"MEANINGS":{},"ANTONYMS":["dissent"],"SYNONYMS":["Assent","Enter","Acquiesce","Give in","Accede"]},"ACCELERANDO":{"MEANINGS":{"1":["Adverb","with increasing speed",[],["here you must play accelerando"]]},"SYNONYMS":["Accelerando"]},"ACCELERATE":{"MEANINGS":{"1":["Verb","move faster",["Intensify","Deepen"],["The car accelerated"]],"2":["Verb","cause to move faster",["Change","Alter","Modify"],["He accelerated the car"]]},"ANTONYMS":["decelerate"],"SYNONYMS":["Quicken","Accelerate","Speed","Speed up"]},"ACCELERATED":{"MEANINGS":{"1":["Adjective","speeded up, as of an academic course",[],["in an accelerated program in school"]]},"ANTONYMS":["decelerate"],"SYNONYMS":["Accelerated","Speed","Quicken","Speed up","Accelerate"]},"ACCELERATES":{"MEANINGS":{},"ANTONYMS":["decelerate"],"SYNONYMS":["Quicken","Accelerate","Speed","Speed up"]},"ACCELERATING":{"MEANINGS":{},"ANTONYMS":["decelerate"],"SYNONYMS":["Quicken","Accelerate","Speed","Speed up"]},"ACCELERATION":{"MEANINGS":{"1":["Noun","an increase in rate of change",["Change","Alteration","Modification"],["modern science caused an acceleration of cultural change"]],"2":["Noun","the act of accelerating; increasing the speed",["Speed","Speeding","Hurrying"],[]],"3":["Noun","(physics) a rate of increase of velocity",["Rate"],[]]},"ANTONYMS":["deceleration"],"SYNONYMS":["Speedup","Quickening","Acceleration"]},"ACCELERATIONS":{"MEANINGS":{},"ANTONYMS":["deceleration"],"SYNONYMS":["Speedup","Quickening","Acceleration"]},"ACCELERATIVE":{"MEANINGS":{"1":["Adjective","tending to increase velocity",[],[]]},"SYNONYMS":["Accelerative","Acceleratory"]},"ACCELERATOR":{"MEANINGS":{"1":["Noun","a pedal that controls the throttle valve",["Pedal","Treadle","Foot pedal","Foot lever"],["he stepped on the gas"]],"2":["Noun","a valve that regulates the supply of fuel to the engine",["Valve"],[]],"4":["Noun","a scientific instrument that increases the kinetic energy of charged particles",["Scientific instrument"],[]]},"ANTONYMS":["anticatalyst"],"SYNONYMS":["Atom smasher","Gas","Throttle","Accelerator pedal","Accelerator"]},"ACCELERATORY":{"MEANINGS":{},"SYNONYMS":["Accelerative","Acceleratory"]},"ACCELERATORS":{"MEANINGS":{},"ANTONYMS":["anticatalyst"],"SYNONYMS":["Atom smasher","Gas","Throttle","Accelerator pedal","Accelerator"]},"ACCELEROMETER":{"MEANINGS":{"1":["Noun","an instrument for measuring the acceleration of aircraft or rockets",["Measuring instrument","Measuring system","Measuring device"],[]]},"SYNONYMS":["Accelerometer"]},"ACCELEROMETERS":{"MEANINGS":{},"SYNONYMS":["Accelerometer"]},"ACCENT":{"MEANINGS":{"1":["Noun","distinctive manner of oral expression",["Pronunciation"],["he couldn't suppress his contemptuous accent","she had a very clear speech pattern"]],"5":["Noun","a diacritical mark used to indicate stress or placed above a vowel to indicate a special pronunciation",["Diacritical mark","Diacritic"],[]]},"SYNONYMS":["Emphasise","Stress","Idiom","Speech pattern","Punctuate"]},"ACCENTED":{"MEANINGS":{},"ANTONYMS":["unstressed","atonic"],"SYNONYMS":["Accent","Accented","Emphasise","Punctuate","Stressed"]},"ACCENTING":{"MEANINGS":{},"SYNONYMS":["Accent","Emphasise","Accentuation","Emphasizing","Accenting"]},"ACCENTOR":{"MEANINGS":{"1":["Noun","small sparrow-like songbird of mountainous regions of Eurasia",["Oscine","Oscine bird"],[]]},"SYNONYMS":["Accentor"]},"ACCENTORS":{"MEANINGS":{},"SYNONYMS":["Accentor"]},"ACCENTS":{"MEANINGS":{},"SYNONYMS":["Emphasise","Stress","Idiom","Speech pattern","Punctuate"]},"ACCENTUAL":{"MEANINGS":{"1":["Adjective","of or pertaining to accent or stress",[],[]],"2":["Adjective","(of verse) having a metric system based on stress rather than syllables or quantity",[],["accentual poetry is based on the number of stresses in a line","accentual rhythm"]]},"ANTONYMS":["quantitative"],"SYNONYMS":["Accentual"]},"ACCENTUATE":{"MEANINGS":{},"SYNONYMS":["Accent","Emphasise","Punctuate","Stress","Emphasize"]},"ACCENTUATED":{"MEANINGS":{},"SYNONYMS":["Accent","Emphasise","Punctuate","Stress","Emphasize"]},"ACCENTUATES":{"MEANINGS":{},"SYNONYMS":["Accent","Emphasise","Punctuate","Stress","Emphasize"]},"ACCENTUATING":{"MEANINGS":{},"SYNONYMS":["Accent","Emphasise","Punctuate","Stress","Emphasize"]},"ACCENTUATION":{"MEANINGS":{"1":["Noun","the use or application of an accent; the relative prominence of syllables in a phrase or utterance",["Stress","Emphasis","Accent"],[]]},"SYNONYMS":["Accentuation","Accenting","Emphasizing"]},"ACCENTUATIONS":{"MEANINGS":{},"SYNONYMS":["Accentuation","Accenting","Emphasizing"]}}